<?xml version="1.0" encoding="ISO-8859-1" ?>
<EntityExport><aWH_ProcedurePricesAndRates><HealthCareProcedure><aWH_InsuranceProcedureDefinition><Code Id="3"><![CDATA[33226]]></Code><ProcedureFamily><aWH_ProcedureFamily><Name>Surgery</Name><NSId>318784133</NSId><Id>38</Id></aWH_ProcedureFamily></ProcedureFamily><Name Id="3"><![CDATA[Reposition l ventric lead]]></Name><MigrationDate Id="15"><![CDATA[--/--/----]]></MigrationDate><NSId Id="1"><![CDATA[318784140]]></NSId><Id Id="2"><![CDATA[275]]></Id><Version Id="3"><![CDATA[1]]></Version></aWH_InsuranceProcedureDefinition></HealthCareProcedure><HealthProcedureRates><aWH_HealthProcedureRateVersionnedByDate><MyOwner><aWH_ProcedurePricesAndRates><NSId Id="1"><![CDATA[318784279]]></NSId><Id Id="2"><![CDATA[1881]]></Id></aWH_ProcedurePricesAndRates></MyOwner><Name Id="3"><![CDATA[]]></Name><MigrationDate Id="15"><![CDATA[--/--/----]]></MigrationDate><NSId Id="1"><![CDATA[318784281]]></NSId><Id Id="2"><![CDATA[1881]]></Id><Version Id="3"><![CDATA[1]]></Version></aWH_HealthProcedureRateVersionnedByDate></HealthProcedureRates><MyRatePlan><aWH_RatePlan><IssuingCompany_Deprecated56><aWFIssuingCompany><Name>W Insurance Company</Name><NSId>318770087</NSId><Id>2</Id></aWFIssuingCompany></IssuingCompany_Deprecated56><Currency Id="3"><![CDATA[22]]></Currency><Context Id="27"><![CDATA[{\rtf1\ansi\ansicpg1252\deff0\deflang1036{\fonttbl{\f0\fnil MS Sans Serif;}}
{\colortbl ;\red0\green0\blue0;}
\viewkind4\uc1\pard\cf1\f0\fs16\par
}
]]></Context><Code Id="31"><![CDATA[SHPT]]></Code><EffectiveDate Id="1"><![CDATA[04/11/2011]]></EffectiveDate><EndDate Id="2"><![CDATA[--/--/----]]></EndDate><CreationDate Id="1"><![CDATA[04/11/2011]]></CreationDate><CreationTime Id="3"><![CDATA[15:36:11]]></CreationTime><Name Id="3"><![CDATA[Standard Health Care Rates Plan]]></Name><MigrationDate Id="15"><![CDATA[--/--/----]]></MigrationDate><NSId Id="1"><![CDATA[318784173]]></NSId><Id Id="2"><![CDATA[6]]></Id><Version Id="3"><![CDATA[2]]></Version></aWH_RatePlan></MyRatePlan><EffectiveDate Id="1"><![CDATA[04/11/2011]]></EffectiveDate><EndDate Id="2"><![CDATA[--/--/----]]></EndDate><CreationDate Id="1"><![CDATA[04/11/2011]]></CreationDate><CreationTime Id="3"><![CDATA[15:36:26]]></CreationTime><Name Id="3"><![CDATA[Reposition l ventric lead]]></Name><MigrationDate Id="15"><![CDATA[--/--/----]]></MigrationDate><NSId Id="1"><![CDATA[318784279]]></NSId><Id Id="2"><![CDATA[1881]]></Id><Version Id="3"><![CDATA[2]]></Version></aWH_ProcedurePricesAndRates></EntityExport>