{
	"description":"",
	"request":{
		"invoiceBuid":"318838395_1"
	},
	"response":{
		"className":"aSPCB_GetInvoice_Out",
		"invoiceId":{
			"statementIdentifier":{
				"issuingCompanyCode":"",
				"name":""
			},
			"buid":""
		},
		"paramEntity":{
			"className":"aSPCB_Invoice",
			"totalAmount":{
				"amount":10.23,
				"currency":"cUSDollar"
			},
			"totalAmountHT":{
				"amount":10.23,
				"currency":"cUSDollar"
			},
			"canceled":false,
			"effectiveDate":"2017-11-20",
			"dueDate":"2017-11-25",
			"status":"cipsNotPaid"
		},
		"grossAmount":{
			"amount":10.23,
			"currency":"cUSDollar"
		},
		"grossDisbursementAmount":{
			"amount":0,
			"currency":"cUSDollar"
		},
		"totalDisbursement":{
			"amount":0,
			"currency":"cUSDollar"
		},
		"bills":[
		],
		"canceled":false,
		"channel":"Manual Check",
		"channelId":{
			"moneyChannelIdentifier":{
				"issuingCompanyCode":"",
				"channelCode":""
			},
			"buid":""
		},
		"payorName":"",
		"issuingCompany":"",
		"buid":"318838395_1"
	},
	"className":"aSLI_manage_accounting",
	"methodName":"GetInvoiceDetails",
	"version":"5.8.1.0",
	"date":"2018-01-03",
	"errors":[
	]
}