{
	"description":"",
	"request":{
		"requestID":{
			"className":"aSPCB_GenericRequirementRequestIdentifier",
			"requestId":"",
			"bUID":"318845938_8",
			"description":""
		},
		"requestTreated":false
	},
	"response":{
		"className":"aSPLI_ThirdPartyRequirementRequestData",
		"requirementRequest":{
			"className":"aSPLI_ThirdPartyRequirementRequest",
			"name":"",
			"documentDescType":"2",
			"otherDocumentDesc":false,
			"isForUnderwriting":false,
			"notifyToServicing":false,
			"requestTreated":false,
			"treatingDate":null,
			"expectedCompletionDate":null,
			"completionDate":null,
			"blockingType":"cBlockActivity",
			"periodicCheckingType":"cNoChecking",
			"periodicCheckingLeadTime":0,
			"periodicCheckingDuration":{
				"quantity":0,
				"unit":"wfDay"
			},
			"periodicCheckingAnnuallyAtDate":null,
			"requestID":"318845938_8_1",
			"requestDate":"2017-08-24",
			"nameUseForPrinting":"Medical certificate "
		},
		"receivedDocuments":[
		],
		"requestedFor":{
			"className":"aSPCB_RequestedForActorData",
			"requestedFor":{
				"data":null,
				"identifier":{
					"className":"aSPCB_ActorIdentifier",
					"bUID":"318842236_7",
					"description":"Elaine Austin 3911 Mewswood Ln, Cadiz, KY 42211"
				}
			},
			"bUID":"318842236_7",
			"dataHistory":[
			]
		},
		"documentDescIdentifier":{
			"className":"aSPCB_GenericRequirementDescIdentifier",
			"code":"",
			"name":"",
			"documentDescType":"",
			"bUID":"318845937_9",
			"description":"Medical certificate, Code: 0"
		},
		"bUID":"318845938_8",
		"dataHistory":[
		]
	},
	"className":"aSF_Manage_RequirementRequest",
	"methodName":"UpdateRequirementRequest",
	"date":"2017-10-09",
	"user":"Nicolas"
}