<?xml version="1.0" encoding="ISO-8859-1" ?>
<EntityExport><aWF_RTF_FormModel><RTFModel><aWF_RTFFormModel_BodyRTFTExt><MyOwner><aWF_RTF_FormModel><NSId Id="1"><![CDATA[318778322]]></NSId><Id Id="2"><![CDATA[80]]></Id></aWF_RTF_FormModel></MyOwner><Fields><aWF_RTF_DraggableFieldDesc><Qualifier><aWFForm_FinalFlatData_Qualifier><NSId Id="1"><![CDATA[318772394]]></NSId><Id Id="2"><![CDATA[555]]></Id></aWFForm_FinalFlatData_Qualifier></Qualifier><Rank Id="6"><![CDATA[0]]></Rank><SizeMax Id="1"><![CDATA[0]]></SizeMax><ForceUpcase Id="2"><![CDATA[Faux]]></ForceUpcase><LongName Id="1"><![CDATA[Date Impression]]></LongName><FieldId Id="13"><![CDATA[0]]></FieldId><MyOwner><aWF_RTFFormModel_BodyRTFTExt><NSId Id="1"><![CDATA[318778313]]></NSId><Id Id="2"><![CDATA[82]]></Id></aWF_RTFFormModel_BodyRTFTExt></MyOwner><Name Id="3"><![CDATA[Date Impression]]></Name><MigrationDate Id="15"><![CDATA[--/--/----]]></MigrationDate><NSId Id="1"><![CDATA[318778316]]></NSId><Id Id="2"><![CDATA[820]]></Id><Version Id="3"><![CDATA[1]]></Version></aWF_RTF_DraggableFieldDesc></Fields><Fields><aWF_RTF_DraggableFieldDesc><Qualifier><aWFForm_FinalFlatData_Qualifier><NSId Id="1"><![CDATA[318772394]]></NSId><Id Id="2"><![CDATA[556]]></Id></aWFForm_FinalFlatData_Qualifier></Qualifier><Rank Id="6"><![CDATA[0]]></Rank><SizeMax Id="1"><![CDATA[0]]></SizeMax><ForceUpcase Id="2"><![CDATA[Faux]]></ForceUpcase><LongName Id="1"><![CDATA[Nom Auteur]]></LongName><FieldId Id="13"><![CDATA[0]]></FieldId><MyOwner><aWF_RTFFormModel_BodyRTFTExt><NSId Id="1"><![CDATA[318778313]]></NSId><Id Id="2"><![CDATA[82]]></Id></aWF_RTFFormModel_BodyRTFTExt></MyOwner><Name Id="3"><![CDATA[Nom Auteur]]></Name><MigrationDate Id="15"><![CDATA[--/--/----]]></MigrationDate><NSId Id="1"><![CDATA[318778316]]></NSId><Id Id="2"><![CDATA[821]]></Id><Version Id="3"><![CDATA[1]]></Version></aWF_RTF_DraggableFieldDesc></Fields><Fields><aWF_RTF_DraggableFieldDesc><Qualifier><aWFForm_FinalFlatData_Qualifier><NSId Id="1"><![CDATA[318772394]]></NSId><Id Id="2"><![CDATA[557]]></Id></aWFForm_FinalFlatData_Qualifier></Qualifier><Rank Id="6"><![CDATA[0]]></Rank><SizeMax Id="1"><![CDATA[0]]></SizeMax><ForceUpcase Id="2"><![CDATA[Faux]]></ForceUpcase><LongName Id="1"><![CDATA[Destinataire courant¤¤/Nom du contact]]></LongName><FieldId Id="13"><![CDATA[0]]></FieldId><MyOwner><aWF_RTFFormModel_BodyRTFTExt><NSId Id="1"><![CDATA[318778313]]></NSId><Id Id="2"><![CDATA[82]]></Id></aWF_RTFFormModel_BodyRTFTExt></MyOwner><Name Id="3"><![CDATA[Destinataire courant¤¤/Nom du contact]]></Name><MigrationDate Id="15"><![CDATA[--/--/----]]></MigrationDate><NSId Id="1"><![CDATA[318778316]]></NSId><Id Id="2"><![CDATA[822]]></Id><Version Id="3"><![CDATA[1]]></Version></aWF_RTF_DraggableFieldDesc></Fields><Fields><aWF_RTF_DraggableFieldDesc><Qualifier><aWFForm_FinalFlatData_Qualifier><NSId Id="1"><![CDATA[318772394]]></NSId><Id Id="2"><![CDATA[558]]></Id></aWFForm_FinalFlatData_Qualifier></Qualifier><Rank Id="6"><![CDATA[0]]></Rank><SizeMax Id="1"><![CDATA[0]]></SizeMax><ForceUpcase Id="2"><![CDATA[Faux]]></ForceUpcase><LongName Id="1"><![CDATA[Destinataire courant¤¤/Correspondance/Adresse postale/Ligne 1]]></LongName><FieldId Id="13"><![CDATA[0]]></FieldId><MyOwner><aWF_RTFFormModel_BodyRTFTExt><NSId Id="1"><![CDATA[318778313]]></NSId><Id Id="2"><![CDATA[82]]></Id></aWF_RTFFormModel_BodyRTFTExt></MyOwner><Name Id="3"><![CDATA[Destinataire courant¤¤/Correspondance/Adresse postale/Ligne 1]]></Name><MigrationDate Id="15"><![CDATA[--/--/----]]></MigrationDate><NSId Id="1"><![CDATA[318778316]]></NSId><Id Id="2"><![CDATA[823]]></Id><Version Id="3"><![CDATA[1]]></Version></aWF_RTF_DraggableFieldDesc></Fields><Fields><aWF_RTF_DraggableFieldDesc><Qualifier><aWFForm_FinalFlatData_Qualifier><NSId Id="1"><![CDATA[318772394]]></NSId><Id Id="2"><![CDATA[559]]></Id></aWFForm_FinalFlatData_Qualifier></Qualifier><Rank Id="6"><![CDATA[0]]></Rank><SizeMax Id="1"><![CDATA[0]]></SizeMax><ForceUpcase Id="2"><![CDATA[Faux]]></ForceUpcase><LongName Id="1"><![CDATA[Destinataire courant¤¤/Correspondance/Adresse postale/Ligne 2]]></LongName><FieldId Id="13"><![CDATA[0]]></FieldId><MyOwner><aWF_RTFFormModel_BodyRTFTExt><NSId Id="1"><![CDATA[318778313]]></NSId><Id Id="2"><![CDATA[82]]></Id></aWF_RTFFormModel_BodyRTFTExt></MyOwner><Name Id="3"><![CDATA[Destinataire courant¤¤/Correspondance/Adresse postale/Ligne 2]]></Name><MigrationDate Id="15"><![CDATA[--/--/----]]></MigrationDate><NSId Id="1"><![CDATA[318778316]]></NSId><Id Id="2"><![CDATA[824]]></Id><Version Id="3"><![CDATA[1]]></Version></aWF_RTF_DraggableFieldDesc></Fields><Fields><aWF_RTF_DraggableFieldDesc><Qualifier><aWFForm_FinalFlatData_Qualifier><NSId Id="1"><![CDATA[318772394]]></NSId><Id Id="2"><![CDATA[560]]></Id></aWFForm_FinalFlatData_Qualifier></Qualifier><Rank Id="6"><![CDATA[0]]></Rank><SizeMax Id="1"><![CDATA[0]]></SizeMax><ForceUpcase Id="2"><![CDATA[Faux]]></ForceUpcase><LongName Id="1"><![CDATA[Destinataire courant¤¤/Correspondance/Adresse postale/Code postal]]></LongName><FieldId Id="13"><![CDATA[0]]></FieldId><MyOwner><aWF_RTFFormModel_BodyRTFTExt><NSId Id="1"><![CDATA[318778313]]></NSId><Id Id="2"><![CDATA[82]]></Id></aWF_RTFFormModel_BodyRTFTExt></MyOwner><Name Id="3"><![CDATA[Destinataire courant¤¤/Correspondance/Adresse postale/Code post]]></Name><MigrationDate Id="15"><![CDATA[--/--/----]]></MigrationDate><NSId Id="1"><![CDATA[318778316]]></NSId><Id Id="2"><![CDATA[825]]></Id><Version Id="3"><![CDATA[1]]></Version></aWF_RTF_DraggableFieldDesc></Fields><Fields><aWF_RTF_DraggableFieldDesc><Qualifier><aWFForm_FinalFlatData_Qualifier><NSId Id="1"><![CDATA[318772394]]></NSId><Id Id="2"><![CDATA[561]]></Id></aWFForm_FinalFlatData_Qualifier></Qualifier><Rank Id="6"><![CDATA[0]]></Rank><SizeMax Id="1"><![CDATA[0]]></SizeMax><ForceUpcase Id="2"><![CDATA[Faux]]></ForceUpcase><LongName Id="1"><![CDATA[Destinataire courant¤¤/Correspondance/Adresse postale/Ville]]></LongName><FieldId Id="13"><![CDATA[0]]></FieldId><MyOwner><aWF_RTFFormModel_BodyRTFTExt><NSId Id="1"><![CDATA[318778313]]></NSId><Id Id="2"><![CDATA[82]]></Id></aWF_RTFFormModel_BodyRTFTExt></MyOwner><Name Id="3"><![CDATA[Destinataire courant¤¤/Correspondance/Adresse postale/Ville]]></Name><MigrationDate Id="15"><![CDATA[--/--/----]]></MigrationDate><NSId Id="1"><![CDATA[318778316]]></NSId><Id Id="2"><![CDATA[826]]></Id><Version Id="3"><![CDATA[1]]></Version></aWF_RTF_DraggableFieldDesc></Fields><Fields><aWF_RTF_DraggableFieldDesc><Qualifier><aWFForm_FinalFlatData_Qualifier><NSId Id="1"><![CDATA[318772394]]></NSId><Id Id="2"><![CDATA[562]]></Id></aWFForm_FinalFlatData_Qualifier></Qualifier><Rank Id="6"><![CDATA[0]]></Rank><SizeMax Id="1"><![CDATA[0]]></SizeMax><ForceUpcase Id="2"><![CDATA[Faux]]></ForceUpcase><LongName Id="1"><![CDATA[Destinataire courant¤¤/Correspondance/Adresse postale/Pays]]></LongName><FieldId Id="13"><![CDATA[0]]></FieldId><MyOwner><aWF_RTFFormModel_BodyRTFTExt><NSId Id="1"><![CDATA[318778313]]></NSId><Id Id="2"><![CDATA[82]]></Id></aWF_RTFFormModel_BodyRTFTExt></MyOwner><Name Id="3"><![CDATA[Destinataire courant¤¤/Correspondance/Adresse postale/Pays]]></Name><MigrationDate Id="15"><![CDATA[--/--/----]]></MigrationDate><NSId Id="1"><![CDATA[318778316]]></NSId><Id Id="2"><![CDATA[827]]></Id><Version Id="3"><![CDATA[1]]></Version></aWF_RTF_DraggableFieldDesc></Fields><Fields><aWF_RTF_DraggableFieldDesc><Qualifier><aWFForm_FinalFlatData_Qualifier><NSId Id="1"><![CDATA[318772394]]></NSId><Id Id="2"><![CDATA[563]]></Id></aWFForm_FinalFlatData_Qualifier></Qualifier><Rank Id="6"><![CDATA[0]]></Rank><SizeMax Id="1"><![CDATA[0]]></SizeMax><ForceUpcase Id="2"><![CDATA[Faux]]></ForceUpcase><LongName Id="1"><![CDATA[Date du Terme/Renouvellement]]></LongName><FieldId Id="13"><![CDATA[0]]></FieldId><MyOwner><aWF_RTFFormModel_BodyRTFTExt><NSId Id="1"><![CDATA[318778313]]></NSId><Id Id="2"><![CDATA[82]]></Id></aWF_RTFFormModel_BodyRTFTExt></MyOwner><Name Id="3"><![CDATA[Date du Terme/Renouvellement]]></Name><MigrationDate Id="15"><![CDATA[--/--/----]]></MigrationDate><NSId Id="1"><![CDATA[318778316]]></NSId><Id Id="2"><![CDATA[828]]></Id><Version Id="3"><![CDATA[1]]></Version></aWF_RTF_DraggableFieldDesc></Fields><Fields><aWF_RTF_DraggableFieldDesc><Qualifier><aWFForm_FinalFlatData_Qualifier><NSId Id="1"><![CDATA[318772394]]></NSId><Id Id="2"><![CDATA[564]]></Id></aWFForm_FinalFlatData_Qualifier></Qualifier><Rank Id="6"><![CDATA[0]]></Rank><SizeMax Id="1"><![CDATA[0]]></SizeMax><ForceUpcase Id="2"><![CDATA[Faux]]></ForceUpcase><LongName Id="1"><![CDATA[Entité offerte/Nom]]></LongName><FieldId Id="13"><![CDATA[0]]></FieldId><MyOwner><aWF_RTFFormModel_BodyRTFTExt><NSId Id="1"><![CDATA[318778313]]></NSId><Id Id="2"><![CDATA[82]]></Id></aWF_RTFFormModel_BodyRTFTExt></MyOwner><Name Id="3"><![CDATA[Entité offerte/Nom]]></Name><MigrationDate Id="15"><![CDATA[--/--/----]]></MigrationDate><NSId Id="1"><![CDATA[318778316]]></NSId><Id Id="2"><![CDATA[829]]></Id><Version Id="3"><![CDATA[1]]></Version></aWF_RTF_DraggableFieldDesc></Fields><Fields><aWF_RTF_DraggableFieldDesc><Qualifier><aWFForm_FinalFlatData_Qualifier><NSId Id="1"><![CDATA[318772394]]></NSId><Id Id="2"><![CDATA[565]]></Id></aWFForm_FinalFlatData_Qualifier></Qualifier><Rank Id="6"><![CDATA[0]]></Rank><SizeMax Id="1"><![CDATA[0]]></SizeMax><ForceUpcase Id="2"><![CDATA[Faux]]></ForceUpcase><LongName Id="1"><![CDATA[Numéro de contrat]]></LongName><FieldId Id="13"><![CDATA[0]]></FieldId><MyOwner><aWF_RTFFormModel_BodyRTFTExt><NSId Id="1"><![CDATA[318778313]]></NSId><Id Id="2"><![CDATA[82]]></Id></aWF_RTFFormModel_BodyRTFTExt></MyOwner><Name Id="3"><![CDATA[Numéro de contrat]]></Name><MigrationDate Id="15"><![CDATA[--/--/----]]></MigrationDate><NSId Id="1"><![CDATA[318778316]]></NSId><Id Id="2"><![CDATA[830]]></Id><Version Id="3"><![CDATA[1]]></Version></aWF_RTF_DraggableFieldDesc></Fields><Fields><aWF_RTF_DraggableFieldDesc><Qualifier><aWFForm_FinalFlatData_Qualifier><NSId Id="1"><![CDATA[318772394]]></NSId><Id Id="2"><![CDATA[566]]></Id></aWFForm_FinalFlatData_Qualifier></Qualifier><Rank Id="6"><![CDATA[0]]></Rank><SizeMax Id="1"><![CDATA[0]]></SizeMax><ForceUpcase Id="2"><![CDATA[Faux]]></ForceUpcase><LongName Id="1"><![CDATA[Souscripteur/Titre]]></LongName><FieldId Id="13"><![CDATA[0]]></FieldId><MyOwner><aWF_RTFFormModel_BodyRTFTExt><NSId Id="1"><![CDATA[318778313]]></NSId><Id Id="2"><![CDATA[82]]></Id></aWF_RTFFormModel_BodyRTFTExt></MyOwner><Name Id="3"><![CDATA[Souscripteur/Titre]]></Name><MigrationDate Id="15"><![CDATA[--/--/----]]></MigrationDate><NSId Id="1"><![CDATA[318778316]]></NSId><Id Id="2"><![CDATA[831]]></Id><Version Id="3"><![CDATA[1]]></Version></aWF_RTF_DraggableFieldDesc></Fields><Fields><aWF_RTF_DraggableFieldDesc><Qualifier><aWFForm_FinalFlatData_Qualifier><NSId Id="1"><![CDATA[318772394]]></NSId><Id Id="2"><![CDATA[567]]></Id></aWFForm_FinalFlatData_Qualifier></Qualifier><Rank Id="6"><![CDATA[0]]></Rank><SizeMax Id="1"><![CDATA[0]]></SizeMax><ForceUpcase Id="2"><![CDATA[Faux]]></ForceUpcase><LongName Id="1"><![CDATA[Société Emettrice/Nom]]></LongName><FieldId Id="13"><![CDATA[0]]></FieldId><MyOwner><aWF_RTFFormModel_BodyRTFTExt><NSId Id="1"><![CDATA[318778313]]></NSId><Id Id="2"><![CDATA[82]]></Id></aWF_RTFFormModel_BodyRTFTExt></MyOwner><Name Id="3"><![CDATA[Société Emettrice/Nom]]></Name><MigrationDate Id="15"><![CDATA[--/--/----]]></MigrationDate><NSId Id="1"><![CDATA[318778316]]></NSId><Id Id="2"><![CDATA[832]]></Id><Version Id="3"><![CDATA[1]]></Version></aWF_RTF_DraggableFieldDesc></Fields><Fields><aWF_RTF_DraggableFieldDesc><Qualifier><aWFForm_FinalFlatData_Qualifier><NSId Id="1"><![CDATA[318772394]]></NSId><Id Id="2"><![CDATA[568]]></Id></aWFForm_FinalFlatData_Qualifier></Qualifier><Rank Id="6"><![CDATA[0]]></Rank><SizeMax Id="1"><![CDATA[0]]></SizeMax><ForceUpcase Id="2"><![CDATA[Faux]]></ForceUpcase><LongName Id="1"><![CDATA[Société Emettrice/Adresse par défaut/Ligne 1]]></LongName><FieldId Id="13"><![CDATA[0]]></FieldId><MyOwner><aWF_RTFFormModel_BodyRTFTExt><NSId Id="1"><![CDATA[318778313]]></NSId><Id Id="2"><![CDATA[82]]></Id></aWF_RTFFormModel_BodyRTFTExt></MyOwner><Name Id="3"><![CDATA[Société Emettrice/Adresse par défaut/Ligne 1]]></Name><MigrationDate Id="15"><![CDATA[--/--/----]]></MigrationDate><NSId Id="1"><![CDATA[318778316]]></NSId><Id Id="2"><![CDATA[833]]></Id><Version Id="3"><![CDATA[1]]></Version></aWF_RTF_DraggableFieldDesc></Fields><Fields><aWF_RTF_DraggableFieldDesc><Qualifier><aWFForm_FinalFlatData_Qualifier><NSId Id="1"><![CDATA[318772394]]></NSId><Id Id="2"><![CDATA[569]]></Id></aWFForm_FinalFlatData_Qualifier></Qualifier><Rank Id="6"><![CDATA[0]]></Rank><SizeMax Id="1"><![CDATA[0]]></SizeMax><ForceUpcase Id="2"><![CDATA[Faux]]></ForceUpcase><LongName Id="1"><![CDATA[Société Emettrice/Adresse par défaut/Code postal]]></LongName><FieldId Id="13"><![CDATA[0]]></FieldId><MyOwner><aWF_RTFFormModel_BodyRTFTExt><NSId Id="1"><![CDATA[318778313]]></NSId><Id Id="2"><![CDATA[82]]></Id></aWF_RTFFormModel_BodyRTFTExt></MyOwner><Name Id="3"><![CDATA[Société Emettrice/Adresse par défaut/Code postal]]></Name><MigrationDate Id="15"><![CDATA[--/--/----]]></MigrationDate><NSId Id="1"><![CDATA[318778316]]></NSId><Id Id="2"><![CDATA[834]]></Id><Version Id="3"><![CDATA[1]]></Version></aWF_RTF_DraggableFieldDesc></Fields><Fields><aWF_RTF_DraggableFieldDesc><Qualifier><aWFForm_FinalFlatData_Qualifier><NSId Id="1"><![CDATA[318772394]]></NSId><Id Id="2"><![CDATA[570]]></Id></aWFForm_FinalFlatData_Qualifier></Qualifier><Rank Id="6"><![CDATA[0]]></Rank><SizeMax Id="1"><![CDATA[0]]></SizeMax><ForceUpcase Id="2"><![CDATA[Faux]]></ForceUpcase><LongName Id="1"><![CDATA[Société Emettrice/Adresse par défaut/Ville]]></LongName><FieldId Id="13"><![CDATA[0]]></FieldId><MyOwner><aWF_RTFFormModel_BodyRTFTExt><NSId Id="1"><![CDATA[318778313]]></NSId><Id Id="2"><![CDATA[82]]></Id></aWF_RTFFormModel_BodyRTFTExt></MyOwner><Name Id="3"><![CDATA[Société Emettrice/Adresse par défaut/Ville]]></Name><MigrationDate Id="15"><![CDATA[--/--/----]]></MigrationDate><NSId Id="1"><![CDATA[318778316]]></NSId><Id Id="2"><![CDATA[835]]></Id><Version Id="3"><![CDATA[1]]></Version></aWF_RTF_DraggableFieldDesc></Fields><Fields><aWF_RTF_DraggableFieldDesc><Qualifier><aWFForm_FinalFlatData_Qualifier><NSId Id="1"><![CDATA[318772394]]></NSId><Id Id="2"><![CDATA[571]]></Id></aWFForm_FinalFlatData_Qualifier></Qualifier><Rank Id="6"><![CDATA[0]]></Rank><SizeMax Id="1"><![CDATA[0]]></SizeMax><ForceUpcase Id="2"><![CDATA[Faux]]></ForceUpcase><LongName Id="1"><![CDATA[Société Emettrice/Adresse par défaut/Pays]]></LongName><FieldId Id="13"><![CDATA[0]]></FieldId><MyOwner><aWF_RTFFormModel_BodyRTFTExt><NSId Id="1"><![CDATA[318778313]]></NSId><Id Id="2"><![CDATA[82]]></Id></aWF_RTFFormModel_BodyRTFTExt></MyOwner><Name Id="3"><![CDATA[Société Emettrice/Adresse par défaut/Pays]]></Name><MigrationDate Id="15"><![CDATA[--/--/----]]></MigrationDate><NSId Id="1"><![CDATA[318778316]]></NSId><Id Id="2"><![CDATA[836]]></Id><Version Id="3"><![CDATA[1]]></Version></aWF_RTF_DraggableFieldDesc></Fields><Fields><aWF_RTF_DraggableFieldDesc><Qualifier><aWFForm_FinalFlatData_Qualifier><NSId Id="1"><![CDATA[318772394]]></NSId><Id Id="2"><![CDATA[572]]></Id></aWFForm_FinalFlatData_Qualifier></Qualifier><Rank Id="6"><![CDATA[1]]></Rank><SizeMax Id="1"><![CDATA[0]]></SizeMax><ForceUpcase Id="2"><![CDATA[Faux]]></ForceUpcase><LongName Id="1"><![CDATA[Emprunts¤1/Type de prêt]]></LongName><FieldId Id="13"><![CDATA[0]]></FieldId><MyOwner><aWF_RTFFormModel_BodyRTFTExt><NSId Id="1"><![CDATA[318778313]]></NSId><Id Id="2"><![CDATA[82]]></Id></aWF_RTFFormModel_BodyRTFTExt></MyOwner><Name Id="3"><![CDATA[Emprunts¤1/Type de prêt]]></Name><MigrationDate Id="15"><![CDATA[--/--/----]]></MigrationDate><NSId Id="1"><![CDATA[318778316]]></NSId><Id Id="2"><![CDATA[837]]></Id><Version Id="3"><![CDATA[1]]></Version></aWF_RTF_DraggableFieldDesc></Fields><Fields><aWF_RTF_DraggableFieldDesc><Qualifier><aWFForm_FinalFlatData_Qualifier><NSId Id="1"><![CDATA[318772394]]></NSId><Id Id="2"><![CDATA[572]]></Id></aWFForm_FinalFlatData_Qualifier></Qualifier><Rank Id="6"><![CDATA[2]]></Rank><SizeMax Id="1"><![CDATA[0]]></SizeMax><ForceUpcase Id="2"><![CDATA[Faux]]></ForceUpcase><LongName Id="1"><![CDATA[Emprunts¤2/Type de prêt]]></LongName><FieldId Id="13"><![CDATA[0]]></FieldId><MyOwner><aWF_RTFFormModel_BodyRTFTExt><NSId Id="1"><![CDATA[318778313]]></NSId><Id Id="2"><![CDATA[82]]></Id></aWF_RTFFormModel_BodyRTFTExt></MyOwner><Name Id="3"><![CDATA[Emprunts¤2/Type de prêt]]></Name><MigrationDate Id="15"><![CDATA[--/--/----]]></MigrationDate><NSId Id="1"><![CDATA[318778316]]></NSId><Id Id="2"><![CDATA[838]]></Id><Version Id="3"><![CDATA[1]]></Version></aWF_RTF_DraggableFieldDesc></Fields><Fields><aWF_RTF_DraggableFieldDesc><Qualifier><aWFForm_FinalFlatData_Qualifier><NSId Id="1"><![CDATA[318772394]]></NSId><Id Id="2"><![CDATA[572]]></Id></aWFForm_FinalFlatData_Qualifier></Qualifier><Rank Id="6"><![CDATA[3]]></Rank><SizeMax Id="1"><![CDATA[0]]></SizeMax><ForceUpcase Id="2"><![CDATA[Faux]]></ForceUpcase><LongName Id="1"><![CDATA[Emprunts¤3/Type de prêt]]></LongName><FieldId Id="13"><![CDATA[0]]></FieldId><MyOwner><aWF_RTFFormModel_BodyRTFTExt><NSId Id="1"><![CDATA[318778313]]></NSId><Id Id="2"><![CDATA[82]]></Id></aWF_RTFFormModel_BodyRTFTExt></MyOwner><Name Id="3"><![CDATA[Emprunts¤3/Type de prêt]]></Name><MigrationDate Id="15"><![CDATA[--/--/----]]></MigrationDate><NSId Id="1"><![CDATA[318778316]]></NSId><Id Id="2"><![CDATA[839]]></Id><Version Id="3"><![CDATA[1]]></Version></aWF_RTF_DraggableFieldDesc></Fields><Fields><aWF_RTF_DraggableFieldDesc><Qualifier><aWFForm_FinalFlatData_Qualifier><NSId Id="1"><![CDATA[318772394]]></NSId><Id Id="2"><![CDATA[573]]></Id></aWFForm_FinalFlatData_Qualifier></Qualifier><Rank Id="6"><![CDATA[1]]></Rank><SizeMax Id="1"><![CDATA[0]]></SizeMax><ForceUpcase Id="2"><![CDATA[Faux]]></ForceUpcase><LongName Id="1"><![CDATA[Emprunts¤1/montant emprunté]]></LongName><FieldId Id="13"><![CDATA[0]]></FieldId><MyOwner><aWF_RTFFormModel_BodyRTFTExt><NSId Id="1"><![CDATA[318778313]]></NSId><Id Id="2"><![CDATA[82]]></Id></aWF_RTFFormModel_BodyRTFTExt></MyOwner><Name Id="3"><![CDATA[Emprunts¤1/montant emprunté]]></Name><MigrationDate Id="15"><![CDATA[--/--/----]]></MigrationDate><NSId Id="1"><![CDATA[318778316]]></NSId><Id Id="2"><![CDATA[840]]></Id><Version Id="3"><![CDATA[1]]></Version></aWF_RTF_DraggableFieldDesc></Fields><Fields><aWF_RTF_DraggableFieldDesc><Qualifier><aWFForm_FinalFlatData_Qualifier><NSId Id="1"><![CDATA[318772394]]></NSId><Id Id="2"><![CDATA[573]]></Id></aWFForm_FinalFlatData_Qualifier></Qualifier><Rank Id="6"><![CDATA[2]]></Rank><SizeMax Id="1"><![CDATA[0]]></SizeMax><ForceUpcase Id="2"><![CDATA[Faux]]></ForceUpcase><LongName Id="1"><![CDATA[Emprunts¤2/montant emprunté]]></LongName><FieldId Id="13"><![CDATA[0]]></FieldId><MyOwner><aWF_RTFFormModel_BodyRTFTExt><NSId Id="1"><![CDATA[318778313]]></NSId><Id Id="2"><![CDATA[82]]></Id></aWF_RTFFormModel_BodyRTFTExt></MyOwner><Name Id="3"><![CDATA[Emprunts¤2/montant emprunté]]></Name><MigrationDate Id="15"><![CDATA[--/--/----]]></MigrationDate><NSId Id="1"><![CDATA[318778316]]></NSId><Id Id="2"><![CDATA[841]]></Id><Version Id="3"><![CDATA[1]]></Version></aWF_RTF_DraggableFieldDesc></Fields><Fields><aWF_RTF_DraggableFieldDesc><Qualifier><aWFForm_FinalFlatData_Qualifier><NSId Id="1"><![CDATA[318772394]]></NSId><Id Id="2"><![CDATA[573]]></Id></aWFForm_FinalFlatData_Qualifier></Qualifier><Rank Id="6"><![CDATA[3]]></Rank><SizeMax Id="1"><![CDATA[0]]></SizeMax><ForceUpcase Id="2"><![CDATA[Faux]]></ForceUpcase><LongName Id="1"><![CDATA[Emprunts¤3/montant emprunté]]></LongName><FieldId Id="13"><![CDATA[0]]></FieldId><MyOwner><aWF_RTFFormModel_BodyRTFTExt><NSId Id="1"><![CDATA[318778313]]></NSId><Id Id="2"><![CDATA[82]]></Id></aWF_RTFFormModel_BodyRTFTExt></MyOwner><Name Id="3"><![CDATA[Emprunts¤3/montant emprunté]]></Name><MigrationDate Id="15"><![CDATA[--/--/----]]></MigrationDate><NSId Id="1"><![CDATA[318778316]]></NSId><Id Id="2"><![CDATA[842]]></Id><Version Id="3"><![CDATA[1]]></Version></aWF_RTF_DraggableFieldDesc></Fields><Fields><aWF_RTF_DraggableFieldDesc><Qualifier><aWFForm_FinalFlatData_Qualifier><NSId Id="1"><![CDATA[318772394]]></NSId><Id Id="2"><![CDATA[574]]></Id></aWFForm_FinalFlatData_Qualifier></Qualifier><Rank Id="6"><![CDATA[1]]></Rank><SizeMax Id="1"><![CDATA[0]]></SizeMax><ForceUpcase Id="2"><![CDATA[Faux]]></ForceUpcase><LongName Id="1"><![CDATA[Emprunts¤1/Devise]]></LongName><FieldId Id="13"><![CDATA[0]]></FieldId><MyOwner><aWF_RTFFormModel_BodyRTFTExt><NSId Id="1"><![CDATA[318778313]]></NSId><Id Id="2"><![CDATA[82]]></Id></aWF_RTFFormModel_BodyRTFTExt></MyOwner><Name Id="3"><![CDATA[Emprunts¤1/Devise]]></Name><MigrationDate Id="15"><![CDATA[--/--/----]]></MigrationDate><NSId Id="1"><![CDATA[318778316]]></NSId><Id Id="2"><![CDATA[843]]></Id><Version Id="3"><![CDATA[1]]></Version></aWF_RTF_DraggableFieldDesc></Fields><Fields><aWF_RTF_DraggableFieldDesc><Qualifier><aWFForm_FinalFlatData_Qualifier><NSId Id="1"><![CDATA[318772394]]></NSId><Id Id="2"><![CDATA[574]]></Id></aWFForm_FinalFlatData_Qualifier></Qualifier><Rank Id="6"><![CDATA[2]]></Rank><SizeMax Id="1"><![CDATA[0]]></SizeMax><ForceUpcase Id="2"><![CDATA[Faux]]></ForceUpcase><LongName Id="1"><![CDATA[Emprunts¤2/Devise]]></LongName><FieldId Id="13"><![CDATA[0]]></FieldId><MyOwner><aWF_RTFFormModel_BodyRTFTExt><NSId Id="1"><![CDATA[318778313]]></NSId><Id Id="2"><![CDATA[82]]></Id></aWF_RTFFormModel_BodyRTFTExt></MyOwner><Name Id="3"><![CDATA[Emprunts¤2/Devise]]></Name><MigrationDate Id="15"><![CDATA[--/--/----]]></MigrationDate><NSId Id="1"><![CDATA[318778316]]></NSId><Id Id="2"><![CDATA[844]]></Id><Version Id="3"><![CDATA[1]]></Version></aWF_RTF_DraggableFieldDesc></Fields><Fields><aWF_RTF_DraggableFieldDesc><Qualifier><aWFForm_FinalFlatData_Qualifier><NSId Id="1"><![CDATA[318772394]]></NSId><Id Id="2"><![CDATA[574]]></Id></aWFForm_FinalFlatData_Qualifier></Qualifier><Rank Id="6"><![CDATA[3]]></Rank><SizeMax Id="1"><![CDATA[0]]></SizeMax><ForceUpcase Id="2"><![CDATA[Faux]]></ForceUpcase><LongName Id="1"><![CDATA[Emprunts¤3/Devise]]></LongName><FieldId Id="13"><![CDATA[0]]></FieldId><MyOwner><aWF_RTFFormModel_BodyRTFTExt><NSId Id="1"><![CDATA[318778313]]></NSId><Id Id="2"><![CDATA[82]]></Id></aWF_RTFFormModel_BodyRTFTExt></MyOwner><Name Id="3"><![CDATA[Emprunts¤3/Devise]]></Name><MigrationDate Id="15"><![CDATA[--/--/----]]></MigrationDate><NSId Id="1"><![CDATA[318778316]]></NSId><Id Id="2"><![CDATA[845]]></Id><Version Id="3"><![CDATA[1]]></Version></aWF_RTF_DraggableFieldDesc></Fields><Fields><aWF_RTF_DraggableFieldDesc><Qualifier><aWFForm_FinalFlatData_Qualifier><NSId Id="1"><![CDATA[318772394]]></NSId><Id Id="2"><![CDATA[575]]></Id></aWFForm_FinalFlatData_Qualifier></Qualifier><Rank Id="6"><![CDATA[1]]></Rank><SizeMax Id="1"><![CDATA[0]]></SizeMax><ForceUpcase Id="2"><![CDATA[Faux]]></ForceUpcase><LongName Id="1"><![CDATA[Emprunts¤1/Durée du prêt en mois]]></LongName><FieldId Id="13"><![CDATA[0]]></FieldId><MyOwner><aWF_RTFFormModel_BodyRTFTExt><NSId Id="1"><![CDATA[318778313]]></NSId><Id Id="2"><![CDATA[82]]></Id></aWF_RTFFormModel_BodyRTFTExt></MyOwner><Name Id="3"><![CDATA[Emprunts¤1/Durée du prêt en mois]]></Name><MigrationDate Id="15"><![CDATA[--/--/----]]></MigrationDate><NSId Id="1"><![CDATA[318778316]]></NSId><Id Id="2"><![CDATA[846]]></Id><Version Id="3"><![CDATA[1]]></Version></aWF_RTF_DraggableFieldDesc></Fields><Fields><aWF_RTF_DraggableFieldDesc><Qualifier><aWFForm_FinalFlatData_Qualifier><NSId Id="1"><![CDATA[318772394]]></NSId><Id Id="2"><![CDATA[575]]></Id></aWFForm_FinalFlatData_Qualifier></Qualifier><Rank Id="6"><![CDATA[2]]></Rank><SizeMax Id="1"><![CDATA[0]]></SizeMax><ForceUpcase Id="2"><![CDATA[Faux]]></ForceUpcase><LongName Id="1"><![CDATA[Emprunts¤2/Durée du prêt en mois]]></LongName><FieldId Id="13"><![CDATA[0]]></FieldId><MyOwner><aWF_RTFFormModel_BodyRTFTExt><NSId Id="1"><![CDATA[318778313]]></NSId><Id Id="2"><![CDATA[82]]></Id></aWF_RTFFormModel_BodyRTFTExt></MyOwner><Name Id="3"><![CDATA[Emprunts¤2/Durée du prêt en mois]]></Name><MigrationDate Id="15"><![CDATA[--/--/----]]></MigrationDate><NSId Id="1"><![CDATA[318778316]]></NSId><Id Id="2"><![CDATA[847]]></Id><Version Id="3"><![CDATA[1]]></Version></aWF_RTF_DraggableFieldDesc></Fields><Fields><aWF_RTF_DraggableFieldDesc><Qualifier><aWFForm_FinalFlatData_Qualifier><NSId Id="1"><![CDATA[318772394]]></NSId><Id Id="2"><![CDATA[575]]></Id></aWFForm_FinalFlatData_Qualifier></Qualifier><Rank Id="6"><![CDATA[3]]></Rank><SizeMax Id="1"><![CDATA[0]]></SizeMax><ForceUpcase Id="2"><![CDATA[Faux]]></ForceUpcase><LongName Id="1"><![CDATA[Emprunts¤3/Durée du prêt en mois]]></LongName><FieldId Id="13"><![CDATA[0]]></FieldId><MyOwner><aWF_RTFFormModel_BodyRTFTExt><NSId Id="1"><![CDATA[318778313]]></NSId><Id Id="2"><![CDATA[82]]></Id></aWF_RTFFormModel_BodyRTFTExt></MyOwner><Name Id="3"><![CDATA[Emprunts¤3/Durée du prêt en mois]]></Name><MigrationDate Id="15"><![CDATA[--/--/----]]></MigrationDate><NSId Id="1"><![CDATA[318778316]]></NSId><Id Id="2"><![CDATA[848]]></Id><Version Id="3"><![CDATA[1]]></Version></aWF_RTF_DraggableFieldDesc></Fields><Parts><aWF_RTF_RTFModelPart><RTFModel><aWF_RTF_FormModel><RTFModel><aWF_RTFFormModel_BodyRTFTExt><Name>Modèle RTF Par Défaut</Name><NSId>318778313</NSId><Id>24</Id></aWF_RTFFormModel_BodyRTFTExt></RTFModel><RecipientManagementKind Id="16"><![CDATA[La même lettre est envoyée en copie aux autres destinataires]]></RecipientManagementKind><InheritContentToo Id="19"><![CDATA[Faux]]></InheritContentToo><FormContextClassDef><aClassDef><Name>aWLI_Contract_FormContentDesc</Name><NSId>218103810</NSId><Id>218110954</Id></aClassDef></FormContextClassDef><ContextName Id="106"><![CDATA[Tout Contrat/Devis : Tout Contrat/Devis]]></ContextName><Qualifiers><aWFForm_RefObjectData_Qualifier><Name>Souscripteur</Name><NSId>318772396</NSId><Id>102</Id></aWFForm_RefObjectData_Qualifier></Qualifiers><Qualifiers><aWFForm_RefObjectData_Qualifier><Name>Unité de Souscription</Name><NSId>318772396</NSId><Id>103</Id></aWFForm_RefObjectData_Qualifier></Qualifiers><Qualifiers><aWFForm_RefObjectData_Qualifier><Name>Société Emettrice</Name><NSId>318772396</NSId><Id>104</Id></aWFForm_RefObjectData_Qualifier></Qualifiers><Qualifiers><aWFForm_CurrentRecipient_Qualifier><Name>Destinataire courant</Name><NSId>318772804</NSId><Id>3</Id></aWFForm_CurrentRecipient_Qualifier></Qualifiers><Active Id="27"><![CDATA[Vrai]]></Active><DefaultModel Id="46"><![CDATA[Faux]]></DefaultModel><kind Id="38"><![CDATA[0]]></kind><UserDefinedPrintingKind><aWFPredefinedPrintingKind><Name>Défaut</Name><NSId>318771451</NSId><Id>55</Id></aWFPredefinedPrintingKind></UserDefinedPrintingKind><InheritedModel Id="70"><![CDATA[Faux]]></InheritedModel><Code Id="105"><![CDATA[EC3]]></Code><DefineRecipients Id="120"><![CDATA[Faux]]></DefineRecipients><MainRecipientKindEnum Id="132"><![CDATA[0]]></MainRecipientKindEnum><OtherRecipientKindsSet Id="133"><![CDATA[(0,0,0,0,0,0,0,0,0,0,0,0,0,0,0,0,0,0,0,0,0,0,0,0,0,0,0,0,0,0,0,0)]]></OtherRecipientKindsSet><Name Id="3"><![CDATA[Entête Contrat sans référence]]></Name><MigrationDate Id="15"><![CDATA[--/--/----]]></MigrationDate><NSId Id="1"><![CDATA[318778322]]></NSId><Id Id="2"><![CDATA[22]]></Id><Version Id="3"><![CDATA[1]]></Version></aWF_RTF_FormModel></RTFModel><MyOwner><aWF_RTFFormModel_BodyRTFTExt><NSId Id="1"><![CDATA[318778313]]></NSId><Id Id="2"><![CDATA[82]]></Id></aWF_RTFFormModel_BodyRTFTExt></MyOwner><Name Id="3"><![CDATA[Entête Contrat sans référence]]></Name><MigrationDate Id="15"><![CDATA[--/--/----]]></MigrationDate><NSId Id="1"><![CDATA[318778375]]></NSId><Id Id="2"><![CDATA[128]]></Id><Version Id="3"><![CDATA[1]]></Version></aWF_RTF_RTFModelPart></Parts><UsedFields><aWF_RTF_DraggableFieldDesc><NSId Id="1"><![CDATA[318778316]]></NSId><Id Id="2"><![CDATA[829]]></Id></aWF_RTF_DraggableFieldDesc></UsedFields><UsedFields><aWF_RTF_DraggableFieldDesc><NSId Id="1"><![CDATA[318778316]]></NSId><Id Id="2"><![CDATA[830]]></Id></aWF_RTF_DraggableFieldDesc></UsedFields><UsedFields><aWF_RTF_DraggableFieldDesc><NSId Id="1"><![CDATA[318778316]]></NSId><Id Id="2"><![CDATA[837]]></Id></aWF_RTF_DraggableFieldDesc></UsedFields><UsedFields><aWF_RTF_DraggableFieldDesc><NSId Id="1"><![CDATA[318778316]]></NSId><Id Id="2"><![CDATA[840]]></Id></aWF_RTF_DraggableFieldDesc></UsedFields><UsedFields><aWF_RTF_DraggableFieldDesc><NSId Id="1"><![CDATA[318778316]]></NSId><Id Id="2"><![CDATA[843]]></Id></aWF_RTF_DraggableFieldDesc></UsedFields><UsedFields><aWF_RTF_DraggableFieldDesc><NSId Id="1"><![CDATA[318778316]]></NSId><Id Id="2"><![CDATA[846]]></Id></aWF_RTF_DraggableFieldDesc></UsedFields><UsedFields><aWF_RTF_DraggableFieldDesc><NSId Id="1"><![CDATA[318778316]]></NSId><Id Id="2"><![CDATA[838]]></Id></aWF_RTF_DraggableFieldDesc></UsedFields><UsedFields><aWF_RTF_DraggableFieldDesc><NSId Id="1"><![CDATA[318778316]]></NSId><Id Id="2"><![CDATA[841]]></Id></aWF_RTF_DraggableFieldDesc></UsedFields><UsedFields><aWF_RTF_DraggableFieldDesc><NSId Id="1"><![CDATA[318778316]]></NSId><Id Id="2"><![CDATA[844]]></Id></aWF_RTF_DraggableFieldDesc></UsedFields><UsedFields><aWF_RTF_DraggableFieldDesc><NSId Id="1"><![CDATA[318778316]]></NSId><Id Id="2"><![CDATA[839]]></Id></aWF_RTF_DraggableFieldDesc></UsedFields><UsedFields><aWF_RTF_DraggableFieldDesc><NSId Id="1"><![CDATA[318778316]]></NSId><Id Id="2"><![CDATA[842]]></Id></aWF_RTF_DraggableFieldDesc></UsedFields><UsedFields><aWF_RTF_DraggableFieldDesc><NSId Id="1"><![CDATA[318778316]]></NSId><Id Id="2"><![CDATA[845]]></Id></aWF_RTF_DraggableFieldDesc></UsedFields><UsedFields><aWF_RTF_DraggableFieldDesc><NSId Id="1"><![CDATA[318778316]]></NSId><Id Id="2"><![CDATA[848]]></Id></aWF_RTF_DraggableFieldDesc></UsedFields><UsedFields><aWF_RTF_DraggableFieldDesc><NSId Id="1"><![CDATA[318778316]]></NSId><Id Id="2"><![CDATA[835]]></Id></aWF_RTF_DraggableFieldDesc></UsedFields><UsedFields><aWF_RTF_DraggableFieldDesc><NSId Id="1"><![CDATA[318778316]]></NSId><Id Id="2"><![CDATA[820]]></Id></aWF_RTF_DraggableFieldDesc></UsedFields><UsedFields><aWF_RTF_DraggableFieldDesc><NSId Id="1"><![CDATA[318778316]]></NSId><Id Id="2"><![CDATA[831]]></Id></aWF_RTF_DraggableFieldDesc></UsedFields><UsedFields><aWF_RTF_DraggableFieldDesc><NSId Id="1"><![CDATA[318778316]]></NSId><Id Id="2"><![CDATA[828]]></Id></aWF_RTF_DraggableFieldDesc></UsedFields><UsedFields><aWF_RTF_DraggableFieldDesc><NSId Id="1"><![CDATA[318778316]]></NSId><Id Id="2"><![CDATA[821]]></Id></aWF_RTF_DraggableFieldDesc></UsedFields><UsedParts><aWF_RTF_RTFModelPart><NSId Id="1"><![CDATA[318778375]]></NSId><Id Id="2"><![CDATA[128]]></Id></aWF_RTF_RTFModelPart></UsedParts><Conditions><aWF_CompositeCondition><SimpleCondition><aWF_SimpleCondition><Field><aWF_RTF_DraggableFieldDesc><NSId Id="1"><![CDATA[318778316]]></NSId><Id Id="2"><![CDATA[838]]></Id></aWF_RTF_DraggableFieldDesc></Field><Operator Id="2"><![CDATA[<>]]></Operator><Value><aWF_BodyFieldDescValue_Cstring><Value Id="1"><![CDATA[]]></Value><Field><aWF_RTF_DraggableFieldDesc><NSId Id="1"><![CDATA[318778316]]></NSId><Id Id="2"><![CDATA[838]]></Id></aWF_RTF_DraggableFieldDesc></Field><LongName Id="6"><![CDATA[]]></LongName><MyOwner><aWF_SimpleCondition><NSId Id="1"><![CDATA[318778359]]></NSId><Id Id="2"><![CDATA[125]]></Id></aWF_SimpleCondition></MyOwner><Name Id="3"><![CDATA[]]></Name><MigrationDate Id="15"><![CDATA[--/--/----]]></MigrationDate><NSId Id="1"><![CDATA[318778334]]></NSId><Id Id="2"><![CDATA[125]]></Id><Version Id="3"><![CDATA[1]]></Version></aWF_BodyFieldDescValue_Cstring></Value><MyOwner><aWF_CompositeCondition><NSId Id="1"><![CDATA[318778362]]></NSId><Id Id="2"><![CDATA[125]]></Id></aWF_CompositeCondition></MyOwner><Name Id="3"><![CDATA[]]></Name><MigrationDate Id="15"><![CDATA[--/--/----]]></MigrationDate><NSId Id="1"><![CDATA[318778359]]></NSId><Id Id="2"><![CDATA[125]]></Id><Version Id="3"><![CDATA[1]]></Version></aWF_SimpleCondition></SimpleCondition><tmpText Id="3"><![CDATA[##Emprunts¤2/Type de prêt## <>  ]]></tmpText><MyOwner><aWF_RTFFormModel_BodyRTFTExt><NSId Id="1"><![CDATA[318778313]]></NSId><Id Id="2"><![CDATA[82]]></Id></aWF_RTFFormModel_BodyRTFTExt></MyOwner><Name Id="3"><![CDATA[Cond_1]]></Name><MigrationDate Id="15"><![CDATA[--/--/----]]></MigrationDate><NSId Id="1"><![CDATA[318778362]]></NSId><Id Id="2"><![CDATA[125]]></Id><Version Id="3"><![CDATA[1]]></Version></aWF_CompositeCondition></Conditions><Conditions><aWF_CompositeCondition><SimpleCondition><aWF_SimpleCondition><Field><aWF_RTF_DraggableFieldDesc><NSId Id="1"><![CDATA[318778316]]></NSId><Id Id="2"><![CDATA[839]]></Id></aWF_RTF_DraggableFieldDesc></Field><Operator Id="2"><![CDATA[<>]]></Operator><Value><aWF_BodyFieldDescValue_Cstring><Value Id="1"><![CDATA[]]></Value><Field><aWF_RTF_DraggableFieldDesc><NSId Id="1"><![CDATA[318778316]]></NSId><Id Id="2"><![CDATA[839]]></Id></aWF_RTF_DraggableFieldDesc></Field><LongName Id="6"><![CDATA[]]></LongName><MyOwner><aWF_SimpleCondition><NSId Id="1"><![CDATA[318778359]]></NSId><Id Id="2"><![CDATA[126]]></Id></aWF_SimpleCondition></MyOwner><Name Id="3"><![CDATA[]]></Name><MigrationDate Id="15"><![CDATA[--/--/----]]></MigrationDate><NSId Id="1"><![CDATA[318778334]]></NSId><Id Id="2"><![CDATA[126]]></Id><Version Id="3"><![CDATA[1]]></Version></aWF_BodyFieldDescValue_Cstring></Value><MyOwner><aWF_CompositeCondition><NSId Id="1"><![CDATA[318778362]]></NSId><Id Id="2"><![CDATA[126]]></Id></aWF_CompositeCondition></MyOwner><Name Id="3"><![CDATA[]]></Name><MigrationDate Id="15"><![CDATA[--/--/----]]></MigrationDate><NSId Id="1"><![CDATA[318778359]]></NSId><Id Id="2"><![CDATA[126]]></Id><Version Id="3"><![CDATA[1]]></Version></aWF_SimpleCondition></SimpleCondition><tmpText Id="3"><![CDATA[##Emprunts¤3/Type de prêt## <>  ]]></tmpText><MyOwner><aWF_RTFFormModel_BodyRTFTExt><NSId Id="1"><![CDATA[318778313]]></NSId><Id Id="2"><![CDATA[82]]></Id></aWF_RTFFormModel_BodyRTFTExt></MyOwner><Name Id="3"><![CDATA[Cond_2]]></Name><MigrationDate Id="15"><![CDATA[--/--/----]]></MigrationDate><NSId Id="1"><![CDATA[318778362]]></NSId><Id Id="2"><![CDATA[126]]></Id><Version Id="3"><![CDATA[1]]></Version></aWF_CompositeCondition></Conditions><Status Id="4"><![CDATA[OK]]></Status><PageBreakAfterText Id="6"><![CDATA[Faux]]></PageBreakAfterText><StoredText Id="2"><![CDATA[]]></StoredText><SubTexts><aWF_SubBodyRTFText><MyOwner><aWF_RTFFormModel_BodyRTFTExt><NSId Id="1"><![CDATA[318778313]]></NSId><Id Id="2"><![CDATA[82]]></Id></aWF_RTFFormModel_BodyRTFTExt></MyOwner><StoredText Id="2"><![CDATA[{\rtf1\ansi\ansicpg1252\deff0\deflang1036{\fonttbl{\f0\fnil\fcharset0 MS Sans Serif;}}
{\colortbl ;\red128\green0\blue0;\red0\green0\blue0;\red0\green168\blue0;}
{\*\generator Msftedit 5.41.21.2509;}\viewkind4\uc1\pard\cf1\f0\fs16 @@0@@\cf2\par
\par
Vos r\'e9f\'e9rences \'e0 rappeler dans toute correspondance: \par
\cf3 ##0##\cf2\par
Contrat: \cf3 ##1##\cf2\par
Emprunts:\par
\cf3 ##2##\cf2 , \cf3 ##3##\cf2  \cf3 ##4##\cf2 , \cf3 ##5##\cf2  mois\par
}
]]></StoredText><DuringComposition Id="4"><![CDATA[Obligatoire]]></DuringComposition><Composed Id="15"><![CDATA[Faux]]></Composed><Numerotation Id="29"><![CDATA[(0,0,0,0,0,0,0,0,0,0)]]></Numerotation><Level Id="30"><![CDATA[0]]></Level><StartOnNextpage Id="36"><![CDATA[Faux]]></StartOnNextpage><Title Id="1"><![CDATA[]]></Title><content Id="4"><![CDATA[]]></content><Name Id="3"><![CDATA[SubText_1]]></Name><MigrationDate Id="15"><![CDATA[--/--/----]]></MigrationDate><NSId Id="1"><![CDATA[318778358]]></NSId><Id Id="2"><![CDATA[552]]></Id><Version Id="3"><![CDATA[1]]></Version></aWF_SubBodyRTFText></SubTexts><SubTexts><aWF_SubBodyRTFText><MyOwner><aWF_RTFFormModel_BodyRTFTExt><NSId Id="1"><![CDATA[318778313]]></NSId><Id Id="2"><![CDATA[82]]></Id></aWF_RTFFormModel_BodyRTFTExt></MyOwner><Condition><aWF_CompositeCondition><NSId Id="1"><![CDATA[318778362]]></NSId><Id Id="2"><![CDATA[125]]></Id></aWF_CompositeCondition></Condition><StoredText Id="2"><![CDATA[]]></StoredText><SubTexts><aWF_SubBodyRTFText><MyOwner><aWF_SubBodyRTFText><NSId Id="1"><![CDATA[318778358]]></NSId><Id Id="2"><![CDATA[553]]></Id></aWF_SubBodyRTFText></MyOwner><StoredText Id="2"><![CDATA[]]></StoredText><SubTexts><aWF_SubBodyRTFText><MyOwner><aWF_SubBodyRTFText><NSId Id="1"><![CDATA[318778358]]></NSId><Id Id="2"><![CDATA[554]]></Id></aWF_SubBodyRTFText></MyOwner><StoredText Id="2"><![CDATA[{\rtf1\ansi\ansicpg1252\deff0\deflang1036{\fonttbl{\f0\fnil\fcharset0 MS Sans Serif;}}
{\colortbl ;\red0\green0\blue0;\red0\green168\blue0;}
{\*\generator Msftedit 5.41.21.2509;}\viewkind4\uc1\pard\cf1\f0\fs16 , \par
\cf2 ##6##\cf1 , \cf2 ##7##\cf1  \cf2 ##8##\cf1 , \cf2 ##6##\cf1  mois \par
}
]]></StoredText><DuringComposition Id="4"><![CDATA[Obligatoire]]></DuringComposition><Composed Id="15"><![CDATA[Faux]]></Composed><Numerotation Id="29"><![CDATA[(0,0,0,0,0,0,0,0,0,0)]]></Numerotation><Level Id="30"><![CDATA[0]]></Level><StartOnNextpage Id="36"><![CDATA[Faux]]></StartOnNextpage><Title Id="1"><![CDATA[]]></Title><content Id="4"><![CDATA[]]></content><Name Id="3"><![CDATA[SubText_1]]></Name><MigrationDate Id="15"><![CDATA[--/--/----]]></MigrationDate><NSId Id="1"><![CDATA[318778358]]></NSId><Id Id="2"><![CDATA[555]]></Id><Version Id="3"><![CDATA[1]]></Version></aWF_SubBodyRTFText></SubTexts><DuringComposition Id="4"><![CDATA[Obligatoire]]></DuringComposition><Composed Id="15"><![CDATA[Faux]]></Composed><Numerotation Id="29"><![CDATA[(0,0,0,0,0,0,0,0,0,0)]]></Numerotation><Level Id="30"><![CDATA[0]]></Level><StartOnNextpage Id="36"><![CDATA[Faux]]></StartOnNextpage><Title Id="1"><![CDATA[]]></Title><content Id="4"><![CDATA[]]></content><Name Id="3"><![CDATA[]]></Name><MigrationDate Id="15"><![CDATA[--/--/----]]></MigrationDate><NSId Id="1"><![CDATA[318778358]]></NSId><Id Id="2"><![CDATA[554]]></Id><Version Id="3"><![CDATA[1]]></Version></aWF_SubBodyRTFText></SubTexts><DuringComposition Id="4"><![CDATA[Obligatoire]]></DuringComposition><Composed Id="15"><![CDATA[Faux]]></Composed><Numerotation Id="29"><![CDATA[(0,0,0,0,0,0,0,0,0,0)]]></Numerotation><Level Id="30"><![CDATA[0]]></Level><StartOnNextpage Id="36"><![CDATA[Faux]]></StartOnNextpage><Title Id="1"><![CDATA[]]></Title><content Id="4"><![CDATA[]]></content><Name Id="3"><![CDATA[SubText_2]]></Name><MigrationDate Id="15"><![CDATA[--/--/----]]></MigrationDate><NSId Id="1"><![CDATA[318778358]]></NSId><Id Id="2"><![CDATA[553]]></Id><Version Id="3"><![CDATA[1]]></Version></aWF_SubBodyRTFText></SubTexts><SubTexts><aWF_SubBodyRTFText><MyOwner><aWF_RTFFormModel_BodyRTFTExt><NSId Id="1"><![CDATA[318778313]]></NSId><Id Id="2"><![CDATA[82]]></Id></aWF_RTFFormModel_BodyRTFTExt></MyOwner><Condition><aWF_CompositeCondition><NSId Id="1"><![CDATA[318778362]]></NSId><Id Id="2"><![CDATA[126]]></Id></aWF_CompositeCondition></Condition><StoredText Id="2"><![CDATA[]]></StoredText><SubTexts><aWF_SubBodyRTFText><MyOwner><aWF_SubBodyRTFText><NSId Id="1"><![CDATA[318778358]]></NSId><Id Id="2"><![CDATA[556]]></Id></aWF_SubBodyRTFText></MyOwner><StoredText Id="2"><![CDATA[]]></StoredText><SubTexts><aWF_SubBodyRTFText><MyOwner><aWF_SubBodyRTFText><NSId Id="1"><![CDATA[318778358]]></NSId><Id Id="2"><![CDATA[557]]></Id></aWF_SubBodyRTFText></MyOwner><StoredText Id="2"><![CDATA[{\rtf1\ansi\ansicpg1252\deff0\deflang1036{\fonttbl{\f0\fnil\fcharset0 MS Sans Serif;}}
{\colortbl ;\red0\green0\blue0;\red0\green168\blue0;}
{\*\generator Msftedit 5.41.21.2509;}\viewkind4\uc1\pard\cf1\f0\fs16 , \par
\cf2 ##9##\cf1 , \cf2 ##10##\cf1  \cf2 ##11##\cf1 , \cf2 ##12##\cf1  mois\par
}
]]></StoredText><DuringComposition Id="4"><![CDATA[Obligatoire]]></DuringComposition><Composed Id="15"><![CDATA[Faux]]></Composed><Numerotation Id="29"><![CDATA[(0,0,0,0,0,0,0,0,0,0)]]></Numerotation><Level Id="30"><![CDATA[0]]></Level><StartOnNextpage Id="36"><![CDATA[Faux]]></StartOnNextpage><Title Id="1"><![CDATA[]]></Title><content Id="4"><![CDATA[]]></content><Name Id="3"><![CDATA[SubText_1]]></Name><MigrationDate Id="15"><![CDATA[--/--/----]]></MigrationDate><NSId Id="1"><![CDATA[318778358]]></NSId><Id Id="2"><![CDATA[558]]></Id><Version Id="3"><![CDATA[1]]></Version></aWF_SubBodyRTFText></SubTexts><DuringComposition Id="4"><![CDATA[Obligatoire]]></DuringComposition><Composed Id="15"><![CDATA[Faux]]></Composed><Numerotation Id="29"><![CDATA[(0,0,0,0,0,0,0,0,0,0)]]></Numerotation><Level Id="30"><![CDATA[0]]></Level><StartOnNextpage Id="36"><![CDATA[Faux]]></StartOnNextpage><Title Id="1"><![CDATA[]]></Title><content Id="4"><![CDATA[]]></content><Name Id="3"><![CDATA[SubText_4]]></Name><MigrationDate Id="15"><![CDATA[--/--/----]]></MigrationDate><NSId Id="1"><![CDATA[318778358]]></NSId><Id Id="2"><![CDATA[557]]></Id><Version Id="3"><![CDATA[1]]></Version></aWF_SubBodyRTFText></SubTexts><DuringComposition Id="4"><![CDATA[Obligatoire]]></DuringComposition><Composed Id="15"><![CDATA[Faux]]></Composed><Numerotation Id="29"><![CDATA[(0,0,0,0,0,0,0,0,0,0)]]></Numerotation><Level Id="30"><![CDATA[0]]></Level><StartOnNextpage Id="36"><![CDATA[Faux]]></StartOnNextpage><Title Id="1"><![CDATA[]]></Title><content Id="4"><![CDATA[]]></content><Name Id="3"><![CDATA[SubText_3]]></Name><MigrationDate Id="15"><![CDATA[--/--/----]]></MigrationDate><NSId Id="1"><![CDATA[318778358]]></NSId><Id Id="2"><![CDATA[556]]></Id><Version Id="3"><![CDATA[1]]></Version></aWF_SubBodyRTFText></SubTexts><SubTexts><aWF_SubBodyRTFText><MyOwner><aWF_RTFFormModel_BodyRTFTExt><NSId Id="1"><![CDATA[318778313]]></NSId><Id Id="2"><![CDATA[82]]></Id></aWF_RTFFormModel_BodyRTFTExt></MyOwner><StoredText Id="2"><![CDATA[{\rtf1\ansi\ansicpg1252\deff0\deflang1036{\fonttbl{\f0\fnil\fcharset0 MS Sans Serif;}}
{\colortbl ;\red0\green0\blue0;\red0\green168\blue0;}
{\*\generator Msftedit 5.41.21.2509;}\viewkind4\uc1\pard\cf1\f0\fs16\par
\par
\par
\cf2 ##13##\cf1 , le \cf2 ##14##\cf1\par
\cf2 ##15##\cf1 ,\par
\par
Nous vous confirmons que le renouvellement de votre contrat \cf2 ##0##\cf1  a bien \'e9t\'e9 effectu\'e9 en date du \cf2 ##16##\cf1 .\par
\par
N'h\'e9sitez pas \'e0 nous contacter si vous souhaitez obtenir des informations compl\'e9mentaires.\par
\par
Nous vous prions d'agr\'e9er, \cf2 ##15##\cf1 , nos salutations distingu\'e9es.\par
\par
\par
\par
\par
\par
\cf2 ##17##\cf1\par
Service Gestion\par
\par
\par
}
]]></StoredText><DuringComposition Id="4"><![CDATA[Obligatoire]]></DuringComposition><Composed Id="15"><![CDATA[Faux]]></Composed><Numerotation Id="29"><![CDATA[(0,0,0,0,0,0,0,0,0,0)]]></Numerotation><Level Id="30"><![CDATA[0]]></Level><StartOnNextpage Id="36"><![CDATA[Faux]]></StartOnNextpage><Title Id="1"><![CDATA[]]></Title><content Id="4"><![CDATA[]]></content><Name Id="3"><![CDATA[SubText_4]]></Name><MigrationDate Id="15"><![CDATA[--/--/----]]></MigrationDate><NSId Id="1"><![CDATA[318778358]]></NSId><Id Id="2"><![CDATA[559]]></Id><Version Id="3"><![CDATA[1]]></Version></aWF_SubBodyRTFText></SubTexts><DuringComposition Id="4"><![CDATA[Obligatoire]]></DuringComposition><Composed Id="15"><![CDATA[Faux]]></Composed><Numerotation Id="29"><![CDATA[(0,0,0,0,0,0,0,0,0,0)]]></Numerotation><Level Id="30"><![CDATA[0]]></Level><Title Id="1"><![CDATA[]]></Title><content Id="4"><![CDATA[]]></content><Name Id="3"><![CDATA[Nouveau Modèle]]></Name><MigrationDate Id="15"><![CDATA[--/--/----]]></MigrationDate><NSId Id="1"><![CDATA[318778313]]></NSId><Id Id="2"><![CDATA[82]]></Id><Version Id="3"><![CDATA[1]]></Version></aWF_RTFFormModel_BodyRTFTExt></RTFModel><RecipientManagementKind Id="16"><![CDATA[La même lettre est envoyée en copie aux autres destinataires]]></RecipientManagementKind><InheritContentToo Id="19"><![CDATA[Faux]]></InheritContentToo><FormContextClassDef><aClassDef><Name Id="2"><![CDATA[aWLOFR_IndividualContract_FormContentDesc]]></Name><NSId Id="1"><![CDATA[218103810]]></NSId><Id Id="2"><![CDATA[218115839]]></Id></aClassDef></FormContextClassDef><ContextName Id="106"><![CDATA[Contrat : Assurance Individuelle Emprunteur]]></ContextName><Qualifiers><aWFForm_FinalFlatData_Qualifier><Format Id="1"><![CDATA[]]></Format><BusinessData><aMethodDesc><Name>PrintDate</Name><NSId>218103824</NSId><Id>936766009736429806</Id><ClassName>aWFFormContentDesc</ClassName></aMethodDesc></BusinessData><MyOwner><aWF_RTF_FormModel><NSId Id="1"><![CDATA[318778322]]></NSId><Id Id="2"><![CDATA[80]]></Id></aWF_RTF_FormModel></MyOwner><Name Id="3"><![CDATA[Date Impression]]></Name><MigrationDate Id="15"><![CDATA[--/--/----]]></MigrationDate><NSId Id="1"><![CDATA[318772394]]></NSId><Id Id="2"><![CDATA[555]]></Id><Version Id="3"><![CDATA[1]]></Version></aWFForm_FinalFlatData_Qualifier></Qualifiers><Qualifiers><aWFForm_FinalFlatData_Qualifier><Format Id="1"><![CDATA[]]></Format><BusinessData><aMethodDesc><Name>LoggedUser</Name><NSId>218103824</NSId><Id>936766009736429810</Id><ClassName>aWFFormContentDesc</ClassName></aMethodDesc></BusinessData><MyOwner><aWF_RTF_FormModel><NSId Id="1"><![CDATA[318778322]]></NSId><Id Id="2"><![CDATA[80]]></Id></aWF_RTF_FormModel></MyOwner><Name Id="3"><![CDATA[Nom Auteur]]></Name><MigrationDate Id="15"><![CDATA[--/--/----]]></MigrationDate><NSId Id="1"><![CDATA[318772394]]></NSId><Id Id="2"><![CDATA[556]]></Id><Version Id="3"><![CDATA[1]]></Version></aWFForm_FinalFlatData_Qualifier></Qualifiers><Qualifiers><aWFForm_CurrentRecipient_Qualifier><FixedNumberOfOccurence Id="1"><![CDATA[Faux]]></FixedNumberOfOccurence><FormModel><aWFFormModel><FormContextClassDef><aClassDef><Name Id="2"><![CDATA[aWF_Recipient_FormContentDesc]]></Name><NSId Id="1"><![CDATA[218103810]]></NSId><Id Id="2"><![CDATA[218109286]]></Id></aClassDef></FormContextClassDef><ContextName Id="106"><![CDATA[Tout modèle]]></ContextName><Qualifiers><aWFForm_FinalFlatData_Qualifier><Format Id="1"><![CDATA[]]></Format><BusinessData><aMethodDesc><Name>ContactName</Name><NSId>218103824</NSId><Id>936772250323910671</Id><ClassName>aWF_Recipient_FormContentDesc</ClassName></aMethodDesc></BusinessData><MyOwner><aWFFormModel><NSId Id="1"><![CDATA[318771107]]></NSId><Id Id="2"><![CDATA[286]]></Id></aWFFormModel></MyOwner><Name Id="3"><![CDATA[Nom du contact]]></Name><MigrationDate Id="15"><![CDATA[--/--/----]]></MigrationDate><NSId Id="1"><![CDATA[318772394]]></NSId><Id Id="2"><![CDATA[557]]></Id><Version Id="3"><![CDATA[1]]></Version></aWFForm_FinalFlatData_Qualifier></Qualifiers><Qualifiers><aWFForm_RefObjectData_Qualifier><FixedNumberOfOccurence Id="1"><![CDATA[Faux]]></FixedNumberOfOccurence><FormModel><aWFFormModel><FormContextClassDef><aClassDef><Name Id="2"><![CDATA[aWF_Correspondance_FormContentDesc]]></Name><NSId Id="1"><![CDATA[218103810]]></NSId><Id Id="2"><![CDATA[218108812]]></Id></aClassDef></FormContextClassDef><ContextName Id="106"><![CDATA[Tout modèle]]></ContextName><Qualifiers><aWFForm_RefObjectData_Qualifier><FixedNumberOfOccurence Id="1"><![CDATA[Faux]]></FixedNumberOfOccurence><FormModel><aWFFormModel><FormContextClassDef><aClassDef><Name Id="2"><![CDATA[aWFAfnorPostalAddress_FormContentDesc]]></Name><NSId Id="1"><![CDATA[218103810]]></NSId><Id Id="2"><![CDATA[218108552]]></Id></aClassDef></FormContextClassDef><ContextName Id="106"><![CDATA[Tout modèle]]></ContextName><Qualifiers><aWFForm_FinalFlatData_Qualifier><Format Id="1"><![CDATA[]]></Format><BusinessData><aOverrideMethodDesc><Name>Line1</Name><NSId>218103824</NSId><Id>936769097817915394</Id><ClassName>aWFAfnorPostalAddress_FormContentDesc</ClassName></aOverrideMethodDesc></BusinessData><MyOwner><aWFFormModel><NSId Id="1"><![CDATA[318771107]]></NSId><Id Id="2"><![CDATA[288]]></Id></aWFFormModel></MyOwner><Name Id="3"><![CDATA[Ligne 1]]></Name><MigrationDate Id="15"><![CDATA[--/--/----]]></MigrationDate><NSId Id="1"><![CDATA[318772394]]></NSId><Id Id="2"><![CDATA[558]]></Id><Version Id="3"><![CDATA[1]]></Version></aWFForm_FinalFlatData_Qualifier></Qualifiers><Qualifiers><aWFForm_FinalFlatData_Qualifier><Format Id="1"><![CDATA[]]></Format><BusinessData><aOverrideMethodDesc><Name>Line2</Name><NSId>218103824</NSId><Id>936769097817915395</Id><ClassName>aWFAfnorPostalAddress_FormContentDesc</ClassName></aOverrideMethodDesc></BusinessData><MyOwner><aWFFormModel><NSId Id="1"><![CDATA[318771107]]></NSId><Id Id="2"><![CDATA[288]]></Id></aWFFormModel></MyOwner><Name Id="3"><![CDATA[Ligne 2]]></Name><MigrationDate Id="15"><![CDATA[--/--/----]]></MigrationDate><NSId Id="1"><![CDATA[318772394]]></NSId><Id Id="2"><![CDATA[559]]></Id><Version Id="3"><![CDATA[1]]></Version></aWFForm_FinalFlatData_Qualifier></Qualifiers><Qualifiers><aWFForm_FinalFlatData_Qualifier><Format Id="1"><![CDATA[]]></Format><BusinessData><aMethodDesc><Name>ZipCode</Name><NSId>218103824</NSId><Id>936763325381869584</Id><ClassName>aWFPostalAddress_FormContentDesc</ClassName></aMethodDesc></BusinessData><MyOwner><aWFFormModel><NSId Id="1"><![CDATA[318771107]]></NSId><Id Id="2"><![CDATA[288]]></Id></aWFFormModel></MyOwner><Name Id="3"><![CDATA[Code postal]]></Name><MigrationDate Id="15"><![CDATA[--/--/----]]></MigrationDate><NSId Id="1"><![CDATA[318772394]]></NSId><Id Id="2"><![CDATA[560]]></Id><Version Id="3"><![CDATA[1]]></Version></aWFForm_FinalFlatData_Qualifier></Qualifiers><Qualifiers><aWFForm_FinalFlatData_Qualifier><Format Id="1"><![CDATA[]]></Format><BusinessData><aMethodDesc><Name>City</Name><NSId>218103824</NSId><Id>936763325381869588</Id><ClassName>aWFPostalAddress_FormContentDesc</ClassName></aMethodDesc></BusinessData><MyOwner><aWFFormModel><NSId Id="1"><![CDATA[318771107]]></NSId><Id Id="2"><![CDATA[288]]></Id></aWFFormModel></MyOwner><Name Id="3"><![CDATA[Ville]]></Name><MigrationDate Id="15"><![CDATA[--/--/----]]></MigrationDate><NSId Id="1"><![CDATA[318772394]]></NSId><Id Id="2"><![CDATA[561]]></Id><Version Id="3"><![CDATA[1]]></Version></aWFForm_FinalFlatData_Qualifier></Qualifiers><Qualifiers><aWFForm_FinalFlatData_Qualifier><Format Id="1"><![CDATA[]]></Format><BusinessData><aMethodDesc><Name>Country</Name><NSId>218103824</NSId><Id>936763325381869569</Id><ClassName>aWFPostalAddress_FormContentDesc</ClassName></aMethodDesc></BusinessData><MyOwner><aWFFormModel><NSId Id="1"><![CDATA[318771107]]></NSId><Id Id="2"><![CDATA[288]]></Id></aWFFormModel></MyOwner><Name Id="3"><![CDATA[Pays]]></Name><MigrationDate Id="15"><![CDATA[--/--/----]]></MigrationDate><NSId Id="1"><![CDATA[318772394]]></NSId><Id Id="2"><![CDATA[562]]></Id><Version Id="3"><![CDATA[1]]></Version></aWFForm_FinalFlatData_Qualifier></Qualifiers><Active Id="27"><![CDATA[Faux]]></Active><DefaultModel Id="46"><![CDATA[Faux]]></DefaultModel><kind Id="38"><![CDATA[0]]></kind><InheritedModel Id="70"><![CDATA[Faux]]></InheritedModel><Code Id="105"><![CDATA[]]></Code><DefineRecipients Id="120"><![CDATA[Faux]]></DefineRecipients><MainRecipientKindEnum Id="132"><![CDATA[0]]></MainRecipientKindEnum><OtherRecipientKindsSet Id="133"><![CDATA[(0,0,0,0,0,0,0,0,0,0,0,0,0,0,0,0,0,0,0,0,0,0,0,0,0,0,0,0,0,0,0,0)]]></OtherRecipientKindsSet><MyOwner><aWFForm_RefObjectData_Qualifier><NSId Id="1"><![CDATA[318772396]]></NSId><Id Id="2"><![CDATA[240]]></Id></aWFForm_RefObjectData_Qualifier></MyOwner><Name Id="3"><![CDATA[Adresse postale]]></Name><MigrationDate Id="15"><![CDATA[--/--/----]]></MigrationDate><NSId Id="1"><![CDATA[318771107]]></NSId><Id Id="2"><![CDATA[288]]></Id><Version Id="3"><![CDATA[1]]></Version></aWFFormModel></FormModel><BusinessData><aMethodDesc><Name>PostalAddress</Name><NSId>218103824</NSId><Id>936770214509412354</Id><ClassName>aWF_Correspondance_FormContentDesc</ClassName></aMethodDesc></BusinessData><MyOwner><aWFFormModel><NSId Id="1"><![CDATA[318771107]]></NSId><Id Id="2"><![CDATA[287]]></Id></aWFFormModel></MyOwner><Name Id="3"><![CDATA[Adresse postale]]></Name><MigrationDate Id="15"><![CDATA[--/--/----]]></MigrationDate><NSId Id="1"><![CDATA[318772396]]></NSId><Id Id="2"><![CDATA[240]]></Id><Version Id="3"><![CDATA[1]]></Version></aWFForm_RefObjectData_Qualifier></Qualifiers><Active Id="27"><![CDATA[Faux]]></Active><DefaultModel Id="46"><![CDATA[Faux]]></DefaultModel><kind Id="38"><![CDATA[0]]></kind><InheritedModel Id="70"><![CDATA[Faux]]></InheritedModel><Code Id="105"><![CDATA[]]></Code><DefineRecipients Id="120"><![CDATA[Faux]]></DefineRecipients><MainRecipientKindEnum Id="132"><![CDATA[0]]></MainRecipientKindEnum><OtherRecipientKindsSet Id="133"><![CDATA[(0,0,0,0,0,0,0,0,0,0,0,0,0,0,0,0,0,0,0,0,0,0,0,0,0,0,0,0,0,0,0,0)]]></OtherRecipientKindsSet><MyOwner><aWFForm_RefObjectData_Qualifier><NSId Id="1"><![CDATA[318772396]]></NSId><Id Id="2"><![CDATA[239]]></Id></aWFForm_RefObjectData_Qualifier></MyOwner><Name Id="3"><![CDATA[Correspondance]]></Name><MigrationDate Id="15"><![CDATA[--/--/----]]></MigrationDate><NSId Id="1"><![CDATA[318771107]]></NSId><Id Id="2"><![CDATA[287]]></Id><Version Id="3"><![CDATA[1]]></Version></aWFFormModel></FormModel><BusinessData><aMethodDesc><Name>Correspondence</Name><NSId>218103824</NSId><Id>936772250323910668</Id><ClassName>aWF_Recipient_FormContentDesc</ClassName></aMethodDesc></BusinessData><MyOwner><aWFFormModel><NSId Id="1"><![CDATA[318771107]]></NSId><Id Id="2"><![CDATA[286]]></Id></aWFFormModel></MyOwner><Name Id="3"><![CDATA[Correspondance]]></Name><MigrationDate Id="15"><![CDATA[--/--/----]]></MigrationDate><NSId Id="1"><![CDATA[318772396]]></NSId><Id Id="2"><![CDATA[239]]></Id><Version Id="3"><![CDATA[1]]></Version></aWFForm_RefObjectData_Qualifier></Qualifiers><Active Id="27"><![CDATA[Faux]]></Active><DefaultModel Id="46"><![CDATA[Faux]]></DefaultModel><kind Id="38"><![CDATA[0]]></kind><InheritedModel Id="70"><![CDATA[Faux]]></InheritedModel><Code Id="105"><![CDATA[]]></Code><DefineRecipients Id="120"><![CDATA[Faux]]></DefineRecipients><MainRecipientKindEnum Id="132"><![CDATA[0]]></MainRecipientKindEnum><OtherRecipientKindsSet Id="133"><![CDATA[(0,0,0,0,0,0,0,0,0,0,0,0,0,0,0,0,0,0,0,0,0,0,0,0,0,0,0,0,0,0,0,0)]]></OtherRecipientKindsSet><MyOwner><aWFForm_CurrentRecipient_Qualifier><NSId Id="1"><![CDATA[318772804]]></NSId><Id Id="2"><![CDATA[13]]></Id></aWFForm_CurrentRecipient_Qualifier></MyOwner><Name Id="3"><![CDATA[Destinataire courant]]></Name><MigrationDate Id="15"><![CDATA[--/--/----]]></MigrationDate><NSId Id="1"><![CDATA[318771107]]></NSId><Id Id="2"><![CDATA[286]]></Id><Version Id="3"><![CDATA[1]]></Version></aWFFormModel></FormModel><BusinessData><aMethodDesc><Name>CurrentRecipient</Name><NSId>218103824</NSId><Id>936766009736429956</Id><ClassName>aWFFormContentDesc</ClassName></aMethodDesc></BusinessData><MyOwner><aWF_RTF_FormModel><NSId Id="1"><![CDATA[318778322]]></NSId><Id Id="2"><![CDATA[80]]></Id></aWF_RTF_FormModel></MyOwner><Name Id="3"><![CDATA[Destinataire courant]]></Name><MigrationDate Id="15"><![CDATA[--/--/----]]></MigrationDate><NSId Id="1"><![CDATA[318772804]]></NSId><Id Id="2"><![CDATA[13]]></Id><Version Id="3"><![CDATA[1]]></Version></aWFForm_CurrentRecipient_Qualifier></Qualifiers><Qualifiers><aWFForm_FinalFlatData_Qualifier><Format Id="1"><![CDATA[]]></Format><BusinessData><aMethodDesc><Name>TermOrRenewalDate</Name><NSId>218103824</NSId><Id>936764003986702411</Id><ClassName>aWF_SubscribedEntity_FormContentDesc</ClassName></aMethodDesc></BusinessData><MyOwner><aWF_RTF_FormModel><NSId Id="1"><![CDATA[318778322]]></NSId><Id Id="2"><![CDATA[80]]></Id></aWF_RTF_FormModel></MyOwner><Name Id="3"><![CDATA[Date du Terme/Renouvellement]]></Name><MigrationDate Id="15"><![CDATA[--/--/----]]></MigrationDate><NSId Id="1"><![CDATA[318772394]]></NSId><Id Id="2"><![CDATA[563]]></Id><Version Id="3"><![CDATA[1]]></Version></aWFForm_FinalFlatData_Qualifier></Qualifiers><Qualifiers><aWFForm_RefObjectData_Qualifier><FixedNumberOfOccurence Id="1"><![CDATA[Faux]]></FixedNumberOfOccurence><FormModel><aWFFormModel><FormContextClassDef><aClassDef><Name Id="2"><![CDATA[aWLI_Product_FormContentDesc]]></Name><NSId Id="1"><![CDATA[218103810]]></NSId><Id Id="2"><![CDATA[218112037]]></Id></aClassDef></FormContextClassDef><ContextName Id="106"><![CDATA[Produit]]></ContextName><Qualifiers><aWFForm_FinalFlatData_Qualifier><Format Id="1"><![CDATA[]]></Format><BusinessData><aMethodDesc><Name>OfferedName</Name><NSId>218103824</NSId><Id>936764012576637011</Id><ClassName>aWF_OfferedEntity_FormContentDesc</ClassName></aMethodDesc></BusinessData><MyOwner><aWFFormModel><NSId Id="1"><![CDATA[318771107]]></NSId><Id Id="2"><![CDATA[289]]></Id></aWFFormModel></MyOwner><Name Id="3"><![CDATA[Nom]]></Name><MigrationDate Id="15"><![CDATA[--/--/----]]></MigrationDate><NSId Id="1"><![CDATA[318772394]]></NSId><Id Id="2"><![CDATA[564]]></Id><Version Id="3"><![CDATA[1]]></Version></aWFForm_FinalFlatData_Qualifier></Qualifiers><Active Id="27"><![CDATA[Faux]]></Active><DefaultModel Id="46"><![CDATA[Faux]]></DefaultModel><kind Id="38"><![CDATA[0]]></kind><InheritedModel Id="70"><![CDATA[Faux]]></InheritedModel><Code Id="105"><![CDATA[]]></Code><DefineRecipients Id="120"><![CDATA[Faux]]></DefineRecipients><MainRecipientKindEnum Id="132"><![CDATA[0]]></MainRecipientKindEnum><OtherRecipientKindsSet Id="133"><![CDATA[(0,0,0,0,0,0,0,0,0,0,0,0,0,0,0,0,0,0,0,0,0,0,0,0,0,0,0,0,0,0,0,0)]]></OtherRecipientKindsSet><MyOwner><aWFForm_RefObjectData_Qualifier><NSId Id="1"><![CDATA[318772396]]></NSId><Id Id="2"><![CDATA[241]]></Id></aWFForm_RefObjectData_Qualifier></MyOwner><Name Id="3"><![CDATA[Entité offerte]]></Name><MigrationDate Id="15"><![CDATA[--/--/----]]></MigrationDate><NSId Id="1"><![CDATA[318771107]]></NSId><Id Id="2"><![CDATA[289]]></Id><Version Id="3"><![CDATA[1]]></Version></aWFFormModel></FormModel><BusinessData><aOverrideMethodDesc><Name>OfferedEntity</Name><NSId>218103824</NSId><Id>936779414329360454</Id><ClassName>aWLI_Contract_FormContentDesc</ClassName></aOverrideMethodDesc></BusinessData><MyOwner><aWF_RTF_FormModel><NSId Id="1"><![CDATA[318778322]]></NSId><Id Id="2"><![CDATA[80]]></Id></aWF_RTF_FormModel></MyOwner><Name Id="3"><![CDATA[Entité offerte]]></Name><MigrationDate Id="15"><![CDATA[--/--/----]]></MigrationDate><NSId Id="1"><![CDATA[318772396]]></NSId><Id Id="2"><![CDATA[241]]></Id><Version Id="3"><![CDATA[1]]></Version></aWFForm_RefObjectData_Qualifier></Qualifiers><Qualifiers><aWFForm_FinalFlatData_Qualifier><Format Id="1"><![CDATA[]]></Format><BusinessData><aMethodDesc><Name>Number</Name><NSId>218103824</NSId><Id>936764008281669672</Id><ClassName>aWF_Contract_FormContentDesc</ClassName></aMethodDesc></BusinessData><MyOwner><aWF_RTF_FormModel><NSId Id="1"><![CDATA[318778322]]></NSId><Id Id="2"><![CDATA[80]]></Id></aWF_RTF_FormModel></MyOwner><Name Id="3"><![CDATA[Numéro de contrat]]></Name><MigrationDate Id="15"><![CDATA[--/--/----]]></MigrationDate><NSId Id="1"><![CDATA[318772394]]></NSId><Id Id="2"><![CDATA[565]]></Id><Version Id="3"><![CDATA[1]]></Version></aWFForm_FinalFlatData_Qualifier></Qualifiers><Qualifiers><aWFForm_RefObjectData_Qualifier><FixedNumberOfOccurence Id="1"><![CDATA[Faux]]></FixedNumberOfOccurence><FormModel><aWFFormModel><FormContextClassDef><aClassDef><Name Id="2"><![CDATA[aWLIPerson_FormContentDesc]]></Name><NSId Id="1"><![CDATA[218103810]]></NSId><Id Id="2"><![CDATA[218110819]]></Id></aClassDef></FormContextClassDef><ContextName Id="106"><![CDATA[Client:Personne Physique]]></ContextName><Qualifiers><aWFForm_FinalFlatData_Qualifier><Format Id="1"><![CDATA[]]></Format><BusinessData><aOverrideMethodDesc><Name>Title</Name><NSId>218103824</NSId><Id>936763321086902362</Id><ClassName>aWFStandardPerson_FormContentDesc</ClassName></aOverrideMethodDesc></BusinessData><MyOwner><aWFFormModel><NSId Id="1"><![CDATA[318771107]]></NSId><Id Id="2"><![CDATA[290]]></Id></aWFFormModel></MyOwner><Name Id="3"><![CDATA[Titre]]></Name><MigrationDate Id="15"><![CDATA[--/--/----]]></MigrationDate><NSId Id="1"><![CDATA[318772394]]></NSId><Id Id="2"><![CDATA[566]]></Id><Version Id="3"><![CDATA[1]]></Version></aWFForm_FinalFlatData_Qualifier></Qualifiers><Active Id="27"><![CDATA[Faux]]></Active><DefaultModel Id="46"><![CDATA[Faux]]></DefaultModel><kind Id="38"><![CDATA[0]]></kind><InheritedModel Id="70"><![CDATA[Faux]]></InheritedModel><Code Id="105"><![CDATA[]]></Code><DefineRecipients Id="120"><![CDATA[Faux]]></DefineRecipients><MainRecipientKindEnum Id="132"><![CDATA[0]]></MainRecipientKindEnum><OtherRecipientKindsSet Id="133"><![CDATA[(0,0,0,0,0,0,0,0,0,0,0,0,0,0,0,0,0,0,0,0,0,0,0,0,0,0,0,0,0,0,0,0)]]></OtherRecipientKindsSet><MyOwner><aWFForm_RefObjectData_Qualifier><NSId Id="1"><![CDATA[318772396]]></NSId><Id Id="2"><![CDATA[242]]></Id></aWFForm_RefObjectData_Qualifier></MyOwner><Name Id="3"><![CDATA[Souscripteur]]></Name><MigrationDate Id="15"><![CDATA[--/--/----]]></MigrationDate><NSId Id="1"><![CDATA[318771107]]></NSId><Id Id="2"><![CDATA[290]]></Id><Version Id="3"><![CDATA[1]]></Version></aWFFormModel></FormModel><BusinessData><aOverrideMethodDesc><Name>Subscriber</Name><NSId>218103824</NSId><Id>936779560358248595</Id><ClassName>aWLI_IndividualContractRoot_FormContentDesc</ClassName></aOverrideMethodDesc></BusinessData><MyOwner><aWF_RTF_FormModel><NSId Id="1"><![CDATA[318778322]]></NSId><Id Id="2"><![CDATA[80]]></Id></aWF_RTF_FormModel></MyOwner><Name Id="3"><![CDATA[Souscripteur]]></Name><MigrationDate Id="15"><![CDATA[--/--/----]]></MigrationDate><NSId Id="1"><![CDATA[318772396]]></NSId><Id Id="2"><![CDATA[242]]></Id><Version Id="3"><![CDATA[1]]></Version></aWFForm_RefObjectData_Qualifier></Qualifiers><Qualifiers><aWFForm_RefObjectData_Qualifier><FixedNumberOfOccurence Id="1"><![CDATA[Faux]]></FixedNumberOfOccurence><FormModel><aWFFormModel><FormContextClassDef><aClassDef><Name Id="2"><![CDATA[aWF_Actor_FormContentDesc]]></Name><NSId Id="1"><![CDATA[218103810]]></NSId><Id Id="2"><![CDATA[218107242]]></Id></aClassDef></FormContextClassDef><ContextName Id="106"><![CDATA[Tout modèle]]></ContextName><Qualifiers><aWFForm_FinalFlatData_Qualifier><Format Id="1"><![CDATA[]]></Format><BusinessData><aMethodDesc><Name>ActorName</Name><NSId>218103824</NSId><Id>936763471410757706</Id><ClassName>aWF_Actor_FormContentDesc</ClassName></aMethodDesc></BusinessData><MyOwner><aWFFormModel><NSId Id="1"><![CDATA[318771107]]></NSId><Id Id="2"><![CDATA[291]]></Id></aWFFormModel></MyOwner><Name Id="3"><![CDATA[Nom]]></Name><MigrationDate Id="15"><![CDATA[--/--/----]]></MigrationDate><NSId Id="1"><![CDATA[318772394]]></NSId><Id Id="2"><![CDATA[567]]></Id><Version Id="3"><![CDATA[1]]></Version></aWFForm_FinalFlatData_Qualifier></Qualifiers><Qualifiers><aWFForm_RefObjectData_Qualifier><FixedNumberOfOccurence Id="1"><![CDATA[Faux]]></FixedNumberOfOccurence><FormModel><aWFFormModel><FormContextClassDef><aClassDef><Name Id="2"><![CDATA[aWFAfnorPostalAddress_FormContentDesc]]></Name><NSId Id="1"><![CDATA[218103810]]></NSId><Id Id="2"><![CDATA[218108552]]></Id></aClassDef></FormContextClassDef><ContextName Id="106"><![CDATA[Tout modèle]]></ContextName><Qualifiers><aWFForm_FinalFlatData_Qualifier><Format Id="1"><![CDATA[]]></Format><BusinessData><aOverrideMethodDesc><Name>Line1</Name><NSId>218103824</NSId><Id>936769097817915394</Id><ClassName>aWFAfnorPostalAddress_FormContentDesc</ClassName></aOverrideMethodDesc></BusinessData><MyOwner><aWFFormModel><NSId Id="1"><![CDATA[318771107]]></NSId><Id Id="2"><![CDATA[292]]></Id></aWFFormModel></MyOwner><Name Id="3"><![CDATA[Ligne 1]]></Name><MigrationDate Id="15"><![CDATA[--/--/----]]></MigrationDate><NSId Id="1"><![CDATA[318772394]]></NSId><Id Id="2"><![CDATA[568]]></Id><Version Id="3"><![CDATA[1]]></Version></aWFForm_FinalFlatData_Qualifier></Qualifiers><Qualifiers><aWFForm_FinalFlatData_Qualifier><Format Id="1"><![CDATA[]]></Format><BusinessData><aMethodDesc><Name>ZipCode</Name><NSId>218103824</NSId><Id>936763325381869584</Id><ClassName>aWFPostalAddress_FormContentDesc</ClassName></aMethodDesc></BusinessData><MyOwner><aWFFormModel><NSId Id="1"><![CDATA[318771107]]></NSId><Id Id="2"><![CDATA[292]]></Id></aWFFormModel></MyOwner><Name Id="3"><![CDATA[Code postal]]></Name><MigrationDate Id="15"><![CDATA[--/--/----]]></MigrationDate><NSId Id="1"><![CDATA[318772394]]></NSId><Id Id="2"><![CDATA[569]]></Id><Version Id="3"><![CDATA[1]]></Version></aWFForm_FinalFlatData_Qualifier></Qualifiers><Qualifiers><aWFForm_FinalFlatData_Qualifier><Format Id="1"><![CDATA[]]></Format><BusinessData><aMethodDesc><Name>City</Name><NSId>218103824</NSId><Id>936763325381869588</Id><ClassName>aWFPostalAddress_FormContentDesc</ClassName></aMethodDesc></BusinessData><MyOwner><aWFFormModel><NSId Id="1"><![CDATA[318771107]]></NSId><Id Id="2"><![CDATA[292]]></Id></aWFFormModel></MyOwner><Name Id="3"><![CDATA[Ville]]></Name><MigrationDate Id="15"><![CDATA[--/--/----]]></MigrationDate><NSId Id="1"><![CDATA[318772394]]></NSId><Id Id="2"><![CDATA[570]]></Id><Version Id="3"><![CDATA[1]]></Version></aWFForm_FinalFlatData_Qualifier></Qualifiers><Qualifiers><aWFForm_FinalFlatData_Qualifier><Format Id="1"><![CDATA[]]></Format><BusinessData><aMethodDesc><Name>Country</Name><NSId>218103824</NSId><Id>936763325381869569</Id><ClassName>aWFPostalAddress_FormContentDesc</ClassName></aMethodDesc></BusinessData><MyOwner><aWFFormModel><NSId Id="1"><![CDATA[318771107]]></NSId><Id Id="2"><![CDATA[292]]></Id></aWFFormModel></MyOwner><Name Id="3"><![CDATA[Pays]]></Name><MigrationDate Id="15"><![CDATA[--/--/----]]></MigrationDate><NSId Id="1"><![CDATA[318772394]]></NSId><Id Id="2"><![CDATA[571]]></Id><Version Id="3"><![CDATA[1]]></Version></aWFForm_FinalFlatData_Qualifier></Qualifiers><Active Id="27"><![CDATA[Faux]]></Active><DefaultModel Id="46"><![CDATA[Faux]]></DefaultModel><kind Id="38"><![CDATA[0]]></kind><InheritedModel Id="70"><![CDATA[Faux]]></InheritedModel><Code Id="105"><![CDATA[]]></Code><DefineRecipients Id="120"><![CDATA[Faux]]></DefineRecipients><MainRecipientKindEnum Id="132"><![CDATA[0]]></MainRecipientKindEnum><OtherRecipientKindsSet Id="133"><![CDATA[(0,0,0,0,0,0,0,0,0,0,0,0,0,0,0,0,0,0,0,0,0,0,0,0,0,0,0,0,0,0,0,0)]]></OtherRecipientKindsSet><MyOwner><aWFForm_RefObjectData_Qualifier><NSId Id="1"><![CDATA[318772396]]></NSId><Id Id="2"><![CDATA[244]]></Id></aWFForm_RefObjectData_Qualifier></MyOwner><Name Id="3"><![CDATA[Adresse par défaut]]></Name><MigrationDate Id="15"><![CDATA[--/--/----]]></MigrationDate><NSId Id="1"><![CDATA[318771107]]></NSId><Id Id="2"><![CDATA[292]]></Id><Version Id="3"><![CDATA[1]]></Version></aWFFormModel></FormModel><BusinessData><aMethodDesc><Name>DefaultAdd</Name><NSId>218103824</NSId><Id>936763471410757737</Id><ClassName>aWF_Actor_FormContentDesc</ClassName></aMethodDesc></BusinessData><MyOwner><aWFFormModel><NSId Id="1"><![CDATA[318771107]]></NSId><Id Id="2"><![CDATA[291]]></Id></aWFFormModel></MyOwner><Name Id="3"><![CDATA[Adresse par défaut]]></Name><MigrationDate Id="15"><![CDATA[--/--/----]]></MigrationDate><NSId Id="1"><![CDATA[318772396]]></NSId><Id Id="2"><![CDATA[244]]></Id><Version Id="3"><![CDATA[1]]></Version></aWFForm_RefObjectData_Qualifier></Qualifiers><Active Id="27"><![CDATA[Faux]]></Active><DefaultModel Id="46"><![CDATA[Faux]]></DefaultModel><kind Id="38"><![CDATA[0]]></kind><InheritedModel Id="70"><![CDATA[Faux]]></InheritedModel><Code Id="105"><![CDATA[]]></Code><DefineRecipients Id="120"><![CDATA[Faux]]></DefineRecipients><MainRecipientKindEnum Id="132"><![CDATA[0]]></MainRecipientKindEnum><OtherRecipientKindsSet Id="133"><![CDATA[(0,0,0,0,0,0,0,0,0,0,0,0,0,0,0,0,0,0,0,0,0,0,0,0,0,0,0,0,0,0,0,0)]]></OtherRecipientKindsSet><MyOwner><aWFForm_RefObjectData_Qualifier><NSId Id="1"><![CDATA[318772396]]></NSId><Id Id="2"><![CDATA[243]]></Id></aWFForm_RefObjectData_Qualifier></MyOwner><Name Id="3"><![CDATA[Société Emettrice]]></Name><MigrationDate Id="15"><![CDATA[--/--/----]]></MigrationDate><NSId Id="1"><![CDATA[318771107]]></NSId><Id Id="2"><![CDATA[291]]></Id><Version Id="3"><![CDATA[1]]></Version></aWFFormModel></FormModel><BusinessData><aMethodDesc><Name>IssuingCompany</Name><NSId>218103824</NSId><Id>936764008281669680</Id><ClassName>aWF_Contract_FormContentDesc</ClassName></aMethodDesc></BusinessData><MyOwner><aWF_RTF_FormModel><NSId Id="1"><![CDATA[318778322]]></NSId><Id Id="2"><![CDATA[80]]></Id></aWF_RTF_FormModel></MyOwner><Name Id="3"><![CDATA[Société Emettrice]]></Name><MigrationDate Id="15"><![CDATA[--/--/----]]></MigrationDate><NSId Id="1"><![CDATA[318772396]]></NSId><Id Id="2"><![CDATA[243]]></Id><Version Id="3"><![CDATA[1]]></Version></aWFForm_RefObjectData_Qualifier></Qualifiers><Qualifiers><aWFForm_OccurencesObjectData_Qualifier><FixedNumberOfOccurences Id="3"><![CDATA[Vrai]]></FixedNumberOfOccurences><Occurences Id="1"><![CDATA[3]]></Occurences><FormModel><aWFFormModel><FormContextClassDef><aClassDef><Name Id="2"><![CDATA[aWLOFR_SingleLoanForIndividualContract_FormContentDesc]]></Name><NSId Id="1"><![CDATA[218103810]]></NSId><Id Id="2"><![CDATA[218115845]]></Id></aClassDef></FormContextClassDef><ContextName Id="106"><![CDATA[Tout modèle]]></ContextName><Qualifiers><aWFForm_FinalFlatData_Qualifier><Format Id="1"><![CDATA[]]></Format><BusinessData><aMethodDesc><Name>LoanKind</Name><NSId>218103824</NSId><Id>936799656510226552</Id><ClassName>aWLO_SingleLoan_FormContentDesc</ClassName></aMethodDesc></BusinessData><MyOwner><aWFFormModel><NSId Id="1"><![CDATA[318771107]]></NSId><Id Id="2"><![CDATA[293]]></Id></aWFFormModel></MyOwner><Name Id="3"><![CDATA[Type de prêt]]></Name><MigrationDate Id="15"><![CDATA[--/--/----]]></MigrationDate><NSId Id="1"><![CDATA[318772394]]></NSId><Id Id="2"><![CDATA[572]]></Id><Version Id="3"><![CDATA[1]]></Version></aWFForm_FinalFlatData_Qualifier></Qualifiers><Qualifiers><aWFForm_FinalFlatData_Qualifier><Format Id="1"><![CDATA[]]></Format><BusinessData><aMethodDesc><Name>LoanAmount</Name><NSId>218103824</NSId><Id>936799656510226464</Id><ClassName>aWLO_SingleLoan_FormContentDesc</ClassName></aMethodDesc></BusinessData><MyOwner><aWFFormModel><NSId Id="1"><![CDATA[318771107]]></NSId><Id Id="2"><![CDATA[293]]></Id></aWFFormModel></MyOwner><Name Id="3"><![CDATA[montant emprunté]]></Name><MigrationDate Id="15"><![CDATA[--/--/----]]></MigrationDate><NSId Id="1"><![CDATA[318772394]]></NSId><Id Id="2"><![CDATA[573]]></Id><Version Id="3"><![CDATA[1]]></Version></aWFForm_FinalFlatData_Qualifier></Qualifiers><Qualifiers><aWFForm_FinalFlatData_Qualifier><Format Id="1"><![CDATA[]]></Format><BusinessData><aMethodDesc><Name>LoanAmountCurrency</Name><NSId>218103824</NSId><Id>936799656510226539</Id><ClassName>aWLO_SingleLoan_FormContentDesc</ClassName></aMethodDesc></BusinessData><MyOwner><aWFFormModel><NSId Id="1"><![CDATA[318771107]]></NSId><Id Id="2"><![CDATA[293]]></Id></aWFFormModel></MyOwner><Name Id="3"><![CDATA[Devise]]></Name><MigrationDate Id="15"><![CDATA[--/--/----]]></MigrationDate><NSId Id="1"><![CDATA[318772394]]></NSId><Id Id="2"><![CDATA[574]]></Id><Version Id="3"><![CDATA[1]]></Version></aWFForm_FinalFlatData_Qualifier></Qualifiers><Qualifiers><aWFForm_FinalFlatData_Qualifier><Format Id="1"><![CDATA[]]></Format><BusinessData><aMethodDesc><Name>LoanDurationInMonths</Name><NSId>218103824</NSId><Id>936799656510226521</Id><ClassName>aWLO_SingleLoan_FormContentDesc</ClassName></aMethodDesc></BusinessData><MyOwner><aWFFormModel><NSId Id="1"><![CDATA[318771107]]></NSId><Id Id="2"><![CDATA[293]]></Id></aWFFormModel></MyOwner><Name Id="3"><![CDATA[Durée du prêt en mois]]></Name><MigrationDate Id="15"><![CDATA[--/--/----]]></MigrationDate><NSId Id="1"><![CDATA[318772394]]></NSId><Id Id="2"><![CDATA[575]]></Id><Version Id="3"><![CDATA[1]]></Version></aWFForm_FinalFlatData_Qualifier></Qualifiers><Active Id="27"><![CDATA[Faux]]></Active><DefaultModel Id="46"><![CDATA[Faux]]></DefaultModel><kind Id="38"><![CDATA[0]]></kind><InheritedModel Id="70"><![CDATA[Faux]]></InheritedModel><Code Id="105"><![CDATA[]]></Code><DefineRecipients Id="120"><![CDATA[Faux]]></DefineRecipients><MainRecipientKindEnum Id="132"><![CDATA[0]]></MainRecipientKindEnum><OtherRecipientKindsSet Id="133"><![CDATA[(0,0,0,0,0,0,0,0,0,0,0,0,0,0,0,0,0,0,0,0,0,0,0,0,0,0,0,0,0,0,0,0)]]></OtherRecipientKindsSet><MyOwner><aWFForm_OccurencesObjectData_Qualifier><NSId Id="1"><![CDATA[318771127]]></NSId><Id Id="2"><![CDATA[36]]></Id></aWFForm_OccurencesObjectData_Qualifier></MyOwner><Name Id="3"><![CDATA[Emprunts]]></Name><MigrationDate Id="15"><![CDATA[--/--/----]]></MigrationDate><NSId Id="1"><![CDATA[318771107]]></NSId><Id Id="2"><![CDATA[293]]></Id><Version Id="3"><![CDATA[1]]></Version></aWFFormModel></FormModel><BusinessData><aOverrideMethodDesc><Name>CoveredLoans</Name><NSId>218103824</NSId><Id>936800395244601353</Id><ClassName>aWLOFR_IndividualContract_FormContentDesc</ClassName></aOverrideMethodDesc></BusinessData><MyOwner><aWF_RTF_FormModel><NSId Id="1"><![CDATA[318778322]]></NSId><Id Id="2"><![CDATA[80]]></Id></aWF_RTF_FormModel></MyOwner><Name Id="3"><![CDATA[Emprunts]]></Name><MigrationDate Id="15"><![CDATA[--/--/----]]></MigrationDate><NSId Id="1"><![CDATA[318771127]]></NSId><Id Id="2"><![CDATA[36]]></Id><Version Id="3"><![CDATA[1]]></Version></aWFForm_OccurencesObjectData_Qualifier></Qualifiers><Active Id="27"><![CDATA[Vrai]]></Active><DefaultModel Id="46"><![CDATA[Faux]]></DefaultModel><kind Id="38"><![CDATA[6]]></kind><UserDefinedPrintingKind><aWFPredefinedPrintingKind><KindValue Id="1"><![CDATA[6]]></KindValue><FormContextClassDef><aClassDef><Name>aWLOFR_IndividualContract_FormContentDesc</Name><NSId>218103810</NSId><Id>218115839</Id></aClassDef></FormContextClassDef><IsAvailableInObject Id="4"><![CDATA[Vrai]]></IsAvailableInObject><IsAvailableInDesktop Id="5"><![CDATA[Vrai]]></IsAvailableInDesktop><FunctionalDomains Id="2"><![CDATA[010000006E17000000000000]]></FunctionalDomains><WithRecipient Id="12"><![CDATA[Vrai]]></WithRecipient><Name Id="3"><![CDATA[Confirmation de renouvellement]]></Name><MigrationDate Id="15"><![CDATA[--/--/----]]></MigrationDate><NSId Id="1"><![CDATA[318771451]]></NSId><Id Id="2"><![CDATA[110]]></Id><Version Id="3"><![CDATA[1]]></Version></aWFPredefinedPrintingKind></UserDefinedPrintingKind><InheritedModel Id="70"><![CDATA[Faux]]></InheritedModel><Code Id="105"><![CDATA[CR-IEM]]></Code><DefineRecipients Id="120"><![CDATA[Vrai]]></DefineRecipients><MainRecipientKindEnum Id="132"><![CDATA[1]]></MainRecipientKindEnum><OtherRecipientKindsSet Id="133"><![CDATA[(0,0,0,0,0,0,0,0,0,0,0,0,0,0,0,0,0,0,0,0,0,0,0,0,0,0,0,0,0,0,0,0)]]></OtherRecipientKindsSet><Name Id="3"><![CDATA[Confirmation renouvellement-Individuelle emprunteur]]></Name><MigrationDate Id="15"><![CDATA[--/--/----]]></MigrationDate><NSId Id="1"><![CDATA[318778322]]></NSId><Id Id="2"><![CDATA[80]]></Id><Version Id="3"><![CDATA[1]]></Version></aWF_RTF_FormModel></EntityExport>