<?xml version="1.0" encoding="ISO-8859-1" ?>
<EntityExport><aEH_FR_ManageNoemieRight_OnPerson_ActivityDesc><Code Id="35"><![CDATA[DNP]]></Code><Resource><aWFX_ResourceRepresentation><RepresentingClassDef><aClassDef><Name>aWLIPerson</Name><NSId>218103810</NSId><Id>218112890</Id></aClassDef></RepresentingClassDef><Description Id="19"><![CDATA[]]></Description><Name Id="3"><![CDATA[Personne physique]]></Name><MigrationDate Id="15"><![CDATA[--/--/----]]></MigrationDate><NSId Id="1"><![CDATA[318796939]]></NSId><Id Id="2"><![CDATA[11]]></Id><Version Id="3"><![CDATA[1]]></Version></aWFX_ResourceRepresentation></Resource><ProcessActivities Id="42"><![CDATA[Vrai]]></ProcessActivities><visibility Id="47"><![CDATA[0]]></visibility><FatalErrorText Id="66"><![CDATA[]]></FatalErrorText><Name Id="3"><![CDATA[Droit Noémie sur personne]]></Name><MigrationDate Id="15"><![CDATA[--/--/----]]></MigrationDate><NSId Id="1"><![CDATA[320405595]]></NSId><Id Id="2"><![CDATA[1]]></Id><Version Id="3"><![CDATA[1]]></Version></aEH_FR_ManageNoemieRight_OnPerson_ActivityDesc></EntityExport>